Workbook

Sheet Dashboard
B2: Made for Doraemon
B4: Sample product (template) | G4: CURRENCY | H4: JPY
B5: 保湿 化粧水 · 36-month financial model · sales start Aug · built 2026-06-18 | H5: =IF(a_currency="USD",a_fx_jpy_per_usd,1) -> 1
B7: Input quality flags: cogs-benchmark, no-payback-within-36m — see Assumptions for what each means.
B9: Key indicators (live — follow the scenario switcher)
B11: 3Y EBITDA | D11: EBITDA MARGIN, YEAR 3 | F11: PAYBACK MONTH | H11: PEAK FUNDING NEED
B12: ='Investment and Cash'!C31 -> -3015200.2 | D12: =IF(SUM('PL Monthly'!AA17:AL17)=0,0,SUM('PL Monthly'!AA35:AL35)/SUM('PL Monthly'!AA17:AL17)) -> -0.20525088 | F12: ='Investment and Cash'!C29 -> n/a | H12: ='Investment and Cash'!C27 -> 3888349.2
B15: PEAK FUNDING (USD) | D15: REVENUE, YEAR 1 | F15: GROSS MARGIN (PRICE - FEES) | H15: NET CONTRIBUTION (M7-12)
B16: ='Investment and Cash'!C28 -> 25922.328 | D16: =SUM('PL Monthly'!C17:N17) -> 1793590.9 | F16: ='Investment and Cash'!C33 -> 0.77742857 | H16: ='Investment and Cash'!C34 -> 0.14786872
B20: Scenario comparison
B21: Scenario | C21: EBITDA Y1 | D21: EBITDA 3Y | E21: Margin Y3 | F21: Payback | G21: Peak funding | H21: Gross Margin | I21: Net Contribution
B22: pessimistic | C22: =-1480208.66589624/a_cur_div -> -1480208.7 | D22: =-4420816.04387649/a_cur_div -> -4420816 | E22: -0.66472998 | F22: n/a | G22: =5041311.05964144/a_cur_div -> 5041311.1 | H22: 0.74778571 | I22: -0.046687943
B23: base | C23: =-1249418.39162667/a_cur_div -> -1249418.4 | D23: =-3015200.21537217/a_cur_div -> -3015200.2 | E23: -0.20525088 | F23: n/a | G23: =3888349.22700065/a_cur_div -> 3888349.2 | H23: 0.77742857 | I23: 0.14786872
B24: optimistic | C24: =-834773.152993455/a_cur_div -> -834773.15 | D24: =-612662.522197003/a_cur_div -> -612662.52 | E24: 0.048312704 | F24: n/a | G24: =2246626.58450954/a_cur_div -> 2246626.6 | H24: 0.79719048 | I24: 0.27423983
B25: Static engine snapshot per scenario; the cards above and all P&L/Cash sheets are live and follow the Assumptions switcher.
B27: Key inputs (live)
B28: Selling price (active scenario) | D28: =a_act_asp_jpy/a_cur_div -> 3500
B29: Unit cost | D29: =a_unit_cogs_jpy/a_cur_div -> 1575
B30: Target market share | D30: =a_act_target_share -> 0.05
B31: Ad spend % (month 1) | D31: =a_act_tacos_y1_start -> 0.25
B32: Launch ad budget floor / mo | D32: =a_ppc_launch_monthly_min_jpy/a_cur_div -> 30000
B33: Launch costs (incl. contingency) | D33: =a_act_capex_total/a_cur_div -> 519200
B35: Model 9fcc27a6-4dce-47b4-81ae-8308eb866f32 · engine fm-7 · shipped on the base scenario · full inputs on the Assumptions sheet

Sheet Criteria
B2: Made for Doraemon
B4: Investment Criteria
B5: Live go / no-go check against the four financial gates. Follows the scenario switcher; the $ gates use the fixed USD memo rate. Green = met.
B7: =IF($C$18=4,"MEETS ALL 4 CRITERIA","NOT MET - "&(4-$C$18)&" OF 4 FAIL") -> NOT MET - 3 OF 4 FAIL
B10: ="Scenario: "&a_scenario&" | "&$C$18&" of 4 met" -> Scenario: base | 1 of 4 met
B12: Criterion | C12: Target | D12: This product | E12: Status
B13: Launch budget — peak cash need stays within budget | C13: max $20,000 | D13: ='Investment and Cash'!C28 -> 25922.328 | E13: =IF(D13<=20000,"PASS","FAIL") -> FAIL
B14: Cumulative revenue, first 6 sales months | C14: min $7,000 | D14: =(SUM('PL Monthly'!C12:H12))*a_cur_div/a_fx_jpy_per_usd -> 4083.3333 | E14: =IF(D14>=7000,"PASS","FAIL") -> FAIL
B15: Gross margin after Amazon fees (referral + FBA) | C15: min 40% | D15: ='Investment and Cash'!C33 -> 0.77742857 | E15: =IF(D15>=0.4,"PASS","FAIL") -> PASS
B16: Net contribution margin at steady state (month 7+) | C16: min 15% | D16: ='Investment and Cash'!C34 -> 0.14786872 | E16: =IF(D16>=0.15,"PASS","FAIL") -> FAIL
C18: =(D13<=20000)+(D14>=7000)+(D15>=0.4)+(D16>=0.15) -> 1
B20: Definitions — Revenue = gross sales (units x selling price, tax-inclusive). Gross margin = (Selling price - referral - FBA) / price. Net contribution margin = (Revenue - COGS - Amazon fees - PPC) / Revenue, at steady state (months 7-12). The $ gates are evaluated in USD at the memo rate regardless of the display currency. Flip the scenario on Assumptions to test each one.

Sheet Assumptions
B2: Made for Doraemon
B4: Assumptions
B5: Every input that drives the model — edit the purple cells, the whole workbook recalculates. Source / confidence / as-of show what each number rests on. 'Structural' rows need a rebuild by the agent.
B7: Volume & demand
B8: Assumption | C8: Value | D8: Unit | E8: What it is & what it drives | F8: Source | G8: Confidence | H8: As of | I8: Key (for the agent)
B9: Niche demand (units / year) | C9: 18000 | D9: units | E9: How many units the whole niche sells on Amazon JP per year. The base of every revenue number: your sales = this demand x your market share. | F9: enrichment.units_360d | G9: med | H9: 2026-06-11 | I9: units_360d
B10: Target market share | C10: 0.05 | D10: ratio | E10: The share of niche demand you aim to capture once ramped up. Drives units sold, and through them every revenue, cost and cash line. | F10: internal default — single new entrant | G10: low | H10: 2026-06-11 | I10: target_share
B11: Market-share cap | C11: 0.25 | D11: ratio | E11: A plausibility ceiling: even optimistic scenarios cannot assume more than this share of the niche. | F11: internal default — plausibility cap | G11: low | H11: 2026-06-11 | I11: share_cap
B12: Ramp-up (months) | C12: 9 | D12: months | E12: How many months it takes to grow from launch to the full target share. Shorter ramp = faster revenue but a bigger first inventory order. | F12: internal default — typical PL ramp | G12: low | H12: 2026-06-11 | I12: ramp_months
B13: Market growth, year 2 | C13: 0.21 | D13: ratio | E13: How much the whole niche grows in year 2 (from search-volume trend). Grows the market, not your share. | F13: niches.search_volume_growth_180d annualized, clamped | G13: low | H13: 2026-06-11 | I13: demand_growth_y2
B14: Market growth, year 3 | C14: 0.21 | D14: ratio | E14: Same as year 2, applied on top in year 3. | F14: niches.search_volume_growth_180d annualized, clamped | G14: low | H14: 2026-06-11 | I14: demand_growth_y3
B15: Launch month (1-12) | C15: 8 | D15: month | E15: The calendar month of the first sales month (M1). Anchors seasonality and the Oct-Dec storage-fee season; every month column shows its calendar month. | F15: build month + lead window (default) | G15: low | H15: 2026-06-11 | I15: launch_calendar_month
B17: Revenue
B18: Assumption | C18: Value | D18: Unit | E18: What it is & what it drives | F18: Source | G18: Confidence | H18: As of | I18: Key (for the agent)
B19: Consumption tax rate (sales) | C19: 0.1 | D19: ratio | E19: JCT inside the Amazon price (10%; 8% for food/beverage). Carved out of every sale: revenue you keep = price / (1 + rate). | F19: NTA standard rate; 8% food only via explicit user override | G19: high | H19: 2026-06-11 | I19: jct_rate_output
B20: Amazon Points | C20: 0.01 | D20: ratio | E20: Seller-funded points Amazon adds to JP listings by default (~1% of price). Reduces revenue. | F20: Amazon JP points default | G20: high | H20: 2026-06-11 | I20: points_rate
B21: Promo discounts — launch | C21: 0.08 | D21: ratio | E21: Coupons and deals as % of sales during the launch window (incl. their Amazon fees). Launch is promo-heavy to win the first reviews and rank. | F21: Axalpha JP coupon/deal fees 2025-06 | G21: low | H21: 2026-06-11 | I21: promo_rate_launch
B22: Launch window (months) | C22: 3 | D22: months | E22: How long the launch-level promo rate and the launch PPC budget floor apply. | F22: internal default | G22: low | H22: 2026-06-11 | I22: promo_launch_months
B23: Promo discounts — steady | C23: 0.02 | D23: ratio | E23: Ongoing coupons/deals as % of sales after the launch window. | F23: Axalpha JP coupon/deal fees 2025-06 | G23: low | H23: 2026-06-11 | I23: promo_rate_steady
B24: Promo fixed cost / month | C24: 0 | D24: jpy | E24: Flat monthly promo spend (e.g. recurring deal-day fees), if any. | F24: internal default | G24: low | H24: 2026-06-11 | I24: promo_fixed_jpy
B25: Return rate | C25: 0.02 | D25: ratio | E25: Share of orders customers return (JP rates are low, 1-7% by category). Reverses revenue; returned units are written off in full. | F25: niches.return_rate_360d | G25: med | H25: 2026-06-11 | I25: return_rate
B27: Product cost & supply
B28: Assumption | C28: Value | D28: Unit | E28: What it is & what it drives | F28: Source | G28: Confidence | H28: As of | I28: Key (for the agent)
B29: Unit cost (procurement) | C29: 1575 | D29: jpy | E29: What one unit costs to buy or manufacture in Japan, before tax. The single biggest profit driver. A wholesale benchmark until a supplier/OEM quote replaces it. | F29: ECのミカタ 掛け率 | G29: low | H29: 2026-06-11 | I29: unit_cogs_jpy
B30: Logistics to Amazon / unit | C30: 50 | D30: jpy | E30: Moving one unit from the supplier to the Amazon warehouse (prep + carrier). | F30: FBA partner carrier (Yamato) | G30: low | H30: 2026-06-11 | I30: logistics_jpy_per_unit
B31: Quality inspection / unit | C31: 0 | D31: jpy | E31: Acceptance testing per unit; usually 0 for wholesale, set it for OEM batches. | F31: internal default — set per OEM contract | G31: low | H31: 2026-06-11 | I31: inspection_jpy_per_unit
B32: Shrinkage & write-offs | C32: 0.01 | D32: ratio | E32: Goods lost or damaged in the supply chain, % of goods cost. | F32: Value Added Resource FBA reimbursement 2025 | G32: low | H32: 2026-06-11 | I32: shrinkage_rate
B33: Returns salvage | C33: 0 | D33: ratio | E33: Share of a returned unit's cost you recover by reselling it. 0 = every return is a full write-off (conservative). | F33: internal default (conservative) | G33: med | H33: 2026-06-11 | I33: return_salvage_rate
B34: Supplier tax-invoice credit | C34: 1 | D34: ratio | E34: 1.0 if the supplier issues a qualified invoice (their JCT is fully recoverable). 0.8/0.5 for non-registered suppliers — the lost share becomes product cost. | F34: NTA invoice system transitional credits | G34: med | H34: 2026-06-11 | I34: supplier_invoice_credit_rate
B35: Minimum order quantity | C35: 0 | D35: units | E35: The smallest batch the supplier accepts. If it exceeds what you need, cash gets locked in extra stock. | F35: no MOQ until a supplier quote provides one | G35: low | H35: 2026-06-11 | I35: moq_units
B36: Supplier prepayment | C36: 0.5 | D36: ratio | E36: Share of the order paid when ordering (rest on delivery). Higher prepay = more cash needed earlier. | F36: JP OEM convention 50% at order / 50% at delivery; set 0 for 掛け払い invoice terms | G36: low | H36: 2026-06-11 | I36: prepay_order_pct
B38: Product size & Amazon category — edit these
B39: Assumption | C39: Value | D39: Unit | E39: What it is & what it drives | F39: Source | G39: Confidence | H39: As of | I39: Key (for the agent)
B40: Package length (mm) | C40: 180 | D40: mm | E40: Longest side of the shipped package. Drives the FBA size tier and the storage volume — enter the real packed dimensions and the fees recompute. | F40: enrichment package dims | G40: high | H40: 2026-06-11 | I40: package_length_mm
B41: Package width (mm) | C41: 60 | D41: mm | E41: Second side of the shipped package. Used for the size tier and storage volume. | F41: enrichment package dims | G41: high | H41: 2026-06-11 | I41: package_width_mm
B42: Package height (mm) | C42: 60 | D42: mm | E42: Third side of the shipped package. Used for the size tier and storage volume. | F42: enrichment package dims | G42: high | H42: 2026-06-11 | I42: package_height_mm
B43: Package weight (g) | C43: 350 | D43: g | E43: Shipped weight including packaging. Together with the size it sets the FBA tier (each tier has a weight ceiling). | F43: enrichment package dims | G43: high | H43: 2026-06-11 | I43: package_weight_g
B44: Amazon fee category | C44: Beauty, health & personal care | D44: category | E44: ="Lists as "&INDEX('Fee Reference'!$C$34:$C$45,a_fee_cat_idx)&" on Amazon — pick the English category; it sets the referral rate." -> Lists as ビューティ・ヘルス・パーソナルケア on Amazon — pick the English category; it sets the referral rate. | F44: mapped from niche category_group (amazon_jp_referral.yaml) | G44: med | H44: 2026-06-11 | I44: amazon_fee_category
B46: Amazon fees — computed from size, category & price (do not edit)
B47: Assumption | C47: Value | D47: Unit | E47: What it is & what it drives | F47: Source | G47: Confidence | H47: As of | I47: Key (for the agent)
B48: Referral fee rate (computed) | C48: =IF(INDEX(a_scn_asp_jpy,2)<=750,INDEX('Fee Reference'!$D$34:$D$45,a_fee_cat_idx),IF(INDEX(a_scn_asp_jpy,2)<=1500,INDEX('Fee Reference'!$E$34:$E$45,a_fee_cat_idx),INDEX('Fee Reference'!$F$34:$F$45,a_fee_cat_idx))) -> 0.104 | D48: ratio | E48: Amazon's category commission, computed from the category + base price band (5% ≤¥750, then the category rate). Applied to price; min 30 JPY/item at use. | F48: amazon_jp_referral.yaml banded by category + base price (tax-excluded) | G48: high | H48: 2026-06-11 | I48: referral_rate_value
B49: FBA fulfillment fee / unit (computed) | C49: =IF(INDEX(a_scn_asp_jpy,2)<=1000,INDEX('Fee Reference'!$J$9:$J$30,a_pkg_tier_idx),INDEX('Fee Reference'!$I$9:$I$30,a_pkg_tier_idx))/(1+a_jct_rate_standard) -> 377.27273 | D49: jpy | E49: ="Size tier "&a_pkg_tier_name&" — recomputed from the package dimensions + weight (net of 10% tax)." -> Size tier 標準3 — recomputed from the package dimensions + weight (net of 10% tax). | F49: amazon_jp_fba_fees.yaml via size tier (published tax-incl -> net) | G49: high | H49: 2026-06-11 | I49: fba_fee_net
B50: Package volume (computed) | C50: =a_package_length_mm*a_package_width_mm*a_package_height_mm/1000000 -> 0.648 | D50: 1000cm3 | E50: The packaged product's volume (units of 1,000 cm3), computed from the dimensions. Drives storage fees. | F50: package dims (L x W x H) | G50: high | H50: 2026-06-11 | I50: unit_vol_1000cm3
B52: Amazon fees — rates & limits (editable)
B53: Assumption | C53: Value | D53: Unit | E53: What it is & what it drives | F53: Source | G53: Confidence | H53: As of | I53: Key (for the agent)
B54: Storage rate Jan-Sep | C54: 5.16 | D54: jpy_per_1000cm3 | E54: Monthly warehouse fee per 1,000 cm3 of stock, January-September season. | F54: Amazon JP pricing 在庫保管手数料 | G54: high | H54: 2026-06-11 | I54: storage_rate_jan_sep
B55: Storage rate Oct-Dec | C55: 9.17 | D55: jpy_per_1000cm3 | E55: The higher Q4 rate — holiday-season storage costs nearly double. | F55: Amazon JP pricing 在庫保管手数料 | G55: high | H55: 2026-06-11 | I55: storage_rate_oct_dec
B56: Refund admin fee | C56: 0.2 | D56: ratio | E56: On a return Amazon gives the referral fee back minus this share (capped). | F56: Amazon refund administration fee | G56: high | H56: 2026-06-11 | I56: refund_admin_pct_of_referral
B57: Refund admin fee cap | C57: 500 | D57: jpy | E57: The maximum refund-admin fee per unit. | F57: same | G57: high | H57: 2026-06-11 | I57: refund_admin_cap_jpy
B58: Consumption tax rate (services) | C58: 0.1 | D58: ratio | E58: The 10% JCT on Amazon fees and logistics. Recoverable for a registered seller — used only to convert published fees to their net cost. | F58: NTA — fee de-JCT divisor, services always 10% | G58: high | H58: 2026-06-11 | I58: jct_rate_standard
B60: Marketing
B61: Assumption | C61: Value | D61: Unit | E61: What it is & what it drives | F61: Source | G61: Confidence | H61: As of | I61: Key (for the agent)
B62: Ad spend % — launch (TACoS) | C62: 0.25 | D62: ratio | E62: Total advertising as % of sales in month 1. Launch needs heavy ads; the rate declines linearly to the year-1 exit level by month 12. | F62: markenote.jp JP CPC ¥50-300 | G62: low | H62: 2026-06-11 | I62: tacos_y1_start
B63: Ad spend % — end of year 1 | C63: 0.15 | D63: ratio | E63: Where the ad-spend share lands after the first year of rank building. | F63: benchmark band | G63: low | H63: 2026-06-11 | I63: tacos_y1_end
B64: Ad spend % — year 2 | C64: 0.12 | D64: ratio | E64: Steadier ad share once reviews and rank exist. | F64: benchmark band | G64: low | H64: 2026-06-11 | I64: tacos_y2
B65: Ad spend % — year 3 | C65: 0.1 | D65: ratio | E65: Mature ad share, mostly defending position. | F65: benchmark band | G65: low | H65: 2026-06-11 | I65: tacos_y3
B66: Launch ad budget floor / month | C66: 30000 | D66: jpy | E66: Minimum monthly ad spend during the launch window, even while sales are tiny — the kick-start budget that buys visibility before revenue exists. | F66: internal default — launch visibility budget floor | G66: low | H66: 2026-06-11 | I66: ppc_launch_monthly_min_jpy
B67: Influencers & affiliates / month | C67: 0 | D67: jpy | E67: Bloggers, social seeding, affiliate fees. 0 unless you plan creator marketing. | F67: internal default — set when creator marketing is planned | G67: low | H67: 2026-06-11 | I67: influencer_monthly_jpy
B68: Content & creative / month | C68: 20000 | D68: jpy | E68: Photography, A+ pages, video — keeping the listing competitive. | F68: photography/A+/video retainer benchmark | G68: low | H68: 2026-06-11 | I68: content_monthly_jpy
B70: Overhead & management fee (the fee covers all admin)
B71: Assumption | C71: Value | D71: Unit | E71: What it is & what it drives | F71: Source | G71: Confidence | H71: As of | I71: Key (for the agent)
B72: Amazon subscription | C72: 4900 | D72: jpy | E72: The Professional selling plan (4,900 JPY/mo + tax), shared across live products. | F72: Amazon JP pricing 大口出品 | G72: high | H72: 2026-06-11 | I72: subscription_monthly_jpy
B73: Product liability insurance | C73: 3000 | D73: jpy | E73: Required by Amazon above ~1M JPY monthly sales; cheap, mandatory. | F73: Marsh Amazon seller insurance | G73: med | H73: 2026-06-11 | I73: insurance_monthly_jpy
B74: Products sharing overhead | C74: 1 | D74: count | E74: How many live products split the management fee, subscription and accounting. 1 = this product carries everything (conservative). | F74: fully loaded (conservative) until the user states otherwise | G74: med | H74: 2026-06-11 | I74: products_sharing_overhead
B75: Management fee — type | C75: fixed | D75: enum | E75: The fee covers management AND all admin overhead (accounting, software, misc). fixed = flat monthly; pct_net_revenue / pct_gross_sales = flex % of sales; hybrid = fixed + flex together (the dynamic option). | F75: default off | G75: high | H75: 2026-06-11 | I75: mgmt_fee_mode
B76: Management fee — fixed / month | C76: 70000 | D76: jpy | E76: The flat part, JPY/month. Default ¥70k absorbs the former admin lines (accounting ~¥50k, software ~¥10k, misc ~¥10k). | F76: absorbs former admin defaults: accounting ¥50k (税理士 ¥500-700k/yr | G76: low | H76: 2026-06-11 | I76: mgmt_fee_fixed_jpy
B77: Management fee — flex % | C77: 0 | D77: ratio | E77: The flex part: % of the chosen sales base. | F77: default off | G77: high | H77: 2026-06-11 | I77: mgmt_fee_pct
B78: Management fee — start month | C78: 1 | D78: month | E78: First month the fee applies. | F78: default | G78: high | H78: 2026-06-11 | I78: mgmt_fee_start_month
B79: Management fee — yearly increase | C79: 0 | D79: ratio | E79: Annual escalation of the fixed part (e.g. 0.10 = +10%/year). | F79: default | G79: high | H79: 2026-06-11 | I79: mgmt_fee_escalation_pct
B81: Launch costs (one-time)
B82: Assumption | C82: Value | D82: Unit | E82: What it is & what it drives | F82: Source | G82: Confidence | H82: As of | I82: Key (for the agent)
B83: Launch: samples | C83: 50000 | D83: jpy | E83: Sample rounds before committing to a supplier. | F83: sample rounds benchmark | G83: low | H83: 2026-06-11 | I83: capex_samples_jpy
B84: Launch: photo & A+ production | C84: 150000 | D84: jpy | E84: The launch content shoot: photos, A+ design, video. | F84: launch photography/A+ production | G84: low | H84: 2026-06-11 | I84: capex_content_jpy
B85: Launch: trademark | C85: 150000 | D85: jpy | E85: JP trademark registration (enables Brand Registry). | F85: Cotobox trademark cost | G85: med | H85: 2026-06-11 | I85: capex_trademark_jpy
B86: Launch: Vine reviews | C86: 22000 | D86: jpy | E86: Amazon Vine — free promo units given to vetted reviewers in exchange for the first honest reviews (the legitimate 'reviews promo'). | F86: Vine JP fees | G86: high | H86: 2026-06-11 | I86: capex_vine_jpy
B87: Launch: certification & lab tests | C87: 100000 | D87: jpy | E87: Category-dependent compliance testing before sale. | F87: category lab tests placeholder — category-dependent | G87: low | H87: 2026-06-11 | I87: capex_certification_jpy
B88: Launch: OEM tooling | C88: 0 | D88: jpy | E88: Molds/tooling for custom manufacturing — comes from the OEM quote. | F88: quote-based; enter with the OEM quote | G88: low | H88: 2026-06-11 | I88: capex_oem_tooling_jpy
B89: Launch: contingency | C89: 0.1 | D89: ratio | E89: Safety margin on top of the itemized launch costs. | F89: contingency on itemized CAPEX | G89: med | H89: 2026-06-11 | I89: capex_contingency_pct
B91: Cash cycle — structural (rebuild to change)
B92: Assumption | C92: Value | D92: Unit | E92: What it is & what it drives | F92: Source | G92: Confidence | H92: As of | I92: Key (for the agent)
B93: Production lead (days) | C93: 30 | D93: days | E93: Supplier needs this long to produce an order. | F93: domestic OEM/wholesale lead | G93: low | H93: 2026-06-11 | I93: production_lead_days
B94: Delivery (days) | C94: 7 | D94: days | E94: Supplier-to-Amazon-warehouse transit. | F94: domestic supplier->FC delivery | G94: med | H94: 2026-06-11 | I94: delivery_days
B95: Inventory cover (days) | C95: 60 | D95: days | E95: How many days of future sales the warehouse should hold. More cover = fewer stockouts but more cash in stock and higher storage fees. | F95: internal default (min 28: low-inventory-fee mitigation) | G95: med | H95: 2026-06-11 | I95: cover_days
B96: Amazon payout cycle (days) | C96: 14 | D96: days | E96: Amazon holds your money this long before paying out (~2 weeks). | F96: Amazon JP disbursement cycle (~14d) | G96: high | H96: 2026-06-11 | I96: settlement_days
B97: Tax settlement window (months) | C97: 3 | D97: months | E97: How often consumption tax is settled with the tax office. Affects cash timing only. | F97: quarterly interim JCT payments | G97: med | H97: 2026-06-11 | I97: jct_filing_interval_months
B99: Memo
B100: Assumption | C100: Value | D100: Unit | E100: What it is & what it drives | F100: Source | G100: Confidence | H100: As of | I100: Key (for the agent)
B101: JPY per USD (memo) | C101: 150 | D101: jpy_per_usd | E101: Only used to show the funding need in dollars for the $20k criterion. | F101: criteria.yaml | G101: med | I101: fx_jpy_per_usd
B103: Seasonality (demand by calendar month)
B104: Index per calendar month, average = 1.0 (1.2 = month sells 20% above average). Sales start in Aug (launch month) — every month column on the P&L shows its calendar month. Flat 1.0 until per-niche seasonality is collected.
B105: Seasonality index | C105: Jan | D105: Feb | E105: Mar | F105: Apr | G105: May | H105: Jun | I105: Jul | J105: Aug | K105: Sep | L105: Oct | M105: Nov | N105: Dec
C106: 1 | D106: 1 | E106: 1 | F106: 1 | G106: 1 | H106: 1 | I106: 1 | J106: 1 | K106: 1 | L106: 1 | M106: 1 | N106: 1
B108: Scenarios
B109: Three one-sided stress bundles. Pick the active one below — every live sheet recalculates. Prices come from the niche's real price band (lower quartile / median / upper quartile).
B110: Scenario | C110: Price ¥ | D110: Ad % M1 | E110: Ad % M12 | F110: Ad % Y2 | G110: Ad % Y3 | H110: Target share
B111: pessimistic | C111: 2800 | D111: 0.3 | E111: 0.2 | F111: 0.17 | G111: 0.15 | H111: =a_target_share*0.7 -> 0.035
B112: base | C112: 3500 | D112: 0.25 | E112: 0.15 | F112: 0.12 | G112: 0.1 | H112: =a_target_share*1 -> 0.05
B113: optimistic | C113: 4200 | D113: 0.22 | E113: 0.12 | F113: 0.09 | G113: 0.07 | H113: =a_target_share*1.3 -> 0.065
B114: ACTIVE SCENARIO | C114: base
B116: Derived (computed — do not edit)
...

Sheet Fee Reference
B2: Made for Doraemon
B4: Fee Reference
B5: The Amazon Japan fee tables that drive the calculator on the Assumptions sheet — reference data, do not edit. Source: sell.amazon.co.jp/pricing, effective 2026-04-01 (referral verified 2026-06-18, FBA 2026-06-04). FBA fees tax-incl; referral tax-excl.
B7: FBA fulfilment fee by size tier (配送代行手数料, tax-incl ¥)
B8: Size tier | C8: Explicit? | D8: max L mm | E8: max W mm | F8: max H mm | G8: max girth cm | H8: max wt g | I8: fee ¥ | J8: fee ¥ (≤¥1,000) | K8: fits
B9: 小型 | C9: 1 | D9: 250 | E9: 180 | F9: 20 | G9: 0 | H9: 250 | I9: 288 | J9: 222 | K9: =IF(C9=1,(a_pkg_longest_mm<=D9)*(a_pkg_mid_mm<=E9)*(a_pkg_shortest_mm<=F9)*(a_package_weight_g<=H9),(a_pkg_girth_cm<=G9)*(a_package_weight_g<=H9)) -> 0
B10: 標準1 | C10: 1 | D10: 350 | E10: 300 | F10: 33 | G10: 0 | H10: 1000 | I10: 318 | J10: 252 | K10: =IF(C10=1,(a_pkg_longest_mm<=D10)*(a_pkg_mid_mm<=E10)*(a_pkg_shortest_mm<=F10)*(a_package_weight_g<=H10),(a_pkg_girth_cm<=G10)*(a_package_weight_g<=H10)) -> 0
B11: 標準2 | C11: 0 | D11: 0 | E11: 0 | F11: 0 | G11: 20 | H11: 2000 | I11: 410 | J11: 344 | K11: =IF(C11=1,(a_pkg_longest_mm<=D11)*(a_pkg_mid_mm<=E11)*(a_pkg_shortest_mm<=F11)*(a_package_weight_g<=H11),(a_pkg_girth_cm<=G11)*(a_package_weight_g<=H11)) -> 0
B12: 標準3 | C12: 0 | D12: 0 | E12: 0 | F12: 0 | G12: 30 | H12: 2000 | I12: 415 | J12: 358 | K12: =IF(C12=1,(a_pkg_longest_mm<=D12)*(a_pkg_mid_mm<=E12)*(a_pkg_shortest_mm<=F12)*(a_package_weight_g<=H12),(a_pkg_girth_cm<=G12)*(a_package_weight_g<=H12)) -> 1
B13: 標準4 | C13: 0 | D13: 0 | E13: 0 | F13: 0 | G13: 40 | H13: 2000 | I13: 420 | J13: 371 | K13: =IF(C13=1,(a_pkg_longest_mm<=D13)*(a_pkg_mid_mm<=E13)*(a_pkg_shortest_mm<=F13)*(a_package_weight_g<=H13),(a_pkg_girth_cm<=G13)*(a_package_weight_g<=H13)) -> 1
B14: 標準5 | C14: 0 | D14: 0 | E14: 0 | F14: 0 | G14: 50 | H14: 2000 | I14: 425 | J14: 379 | K14: =IF(C14=1,(a_pkg_longest_mm<=D14)*(a_pkg_mid_mm<=E14)*(a_pkg_shortest_mm<=F14)*(a_package_weight_g<=H14),(a_pkg_girth_cm<=G14)*(a_package_weight_g<=H14)) -> 1
B15: 標準6 | C15: 0 | D15: 0 | E15: 0 | F15: 0 | G15: 60 | H15: 2000 | I15: 430 | J15: 391 | K15: =IF(C15=1,(a_pkg_longest_mm<=D15)*(a_pkg_mid_mm<=E15)*(a_pkg_shortest_mm<=F15)*(a_package_weight_g<=H15),(a_pkg_girth_cm<=G15)*(a_package_weight_g<=H15)) -> 1
B16: 標準7 | C16: 0 | D16: 0 | E16: 0 | F16: 0 | G16: 80 | H16: 5000 | I16: 472 | J16: 427 | K16: =IF(C16=1,(a_pkg_longest_mm<=D16)*(a_pkg_mid_mm<=E16)*(a_pkg_shortest_mm<=F16)*(a_package_weight_g<=H16),(a_pkg_girth_cm<=G16)*(a_package_weight_g<=H16)) -> 1
B17: 標準8 | C17: 0 | D17: 0 | E17: 0 | F17: 0 | G17: 100 | H17: 9000 | I17: 532 | J17: 466 | K17: =IF(C17=1,(a_pkg_longest_mm<=D17)*(a_pkg_mid_mm<=E17)*(a_pkg_shortest_mm<=F17)*(a_package_weight_g<=H17),(a_pkg_girth_cm<=G17)*(a_package_weight_g<=H17)) -> 1
B18: 大型1 | C18: 0 | D18: 0 | E18: 0 | F18: 0 | G18: 60 | H18: 2000 | I18: 589 | J18: 523 | K18: =IF(C18=1,(a_pkg_longest_mm<=D18)*(a_pkg_mid_mm<=E18)*(a_pkg_shortest_mm<=F18)*(a_package_weight_g<=H18),(a_pkg_girth_cm<=G18)*(a_package_weight_g<=H18)) -> 1
B19: 大型2 | C19: 0 | D19: 0 | E19: 0 | F19: 0 | G19: 80 | H19: 5000 | I19: 624 | J19: 558 | K19: =IF(C19=1,(a_pkg_longest_mm<=D19)*(a_pkg_mid_mm<=E19)*(a_pkg_shortest_mm<=F19)*(a_package_weight_g<=H19),(a_pkg_girth_cm<=G19)*(a_package_weight_g<=H19)) -> 1
B20: 大型3 | C20: 0 | D20: 0 | E20: 0 | F20: 0 | G20: 100 | H20: 10000 | I20: 675 | J20: 609 | K20: =IF(C20=1,(a_pkg_longest_mm<=D20)*(a_pkg_mid_mm<=E20)*(a_pkg_shortest_mm<=F20)*(a_package_weight_g<=H20),(a_pkg_girth_cm<=G20)*(a_package_weight_g<=H20)) -> 1
... B29: 特大型4 | C29: 0 | D29: 0 | E29: 0 | F29: 0 | G29: 260 | H29: 50000 | I29: 5625 | J29: 5559 | K29: =IF(C29=1,(a_pkg_longest_mm<=D29)*(a_pkg_mid_mm<=E29)*(a_pkg_shortest_mm<=F29)*(a_package_weight_g<=H29),(a_pkg_girth_cm<=G29)*(a_package_weight_g<=H29)) -> 1
B30: 特大型5 | C30: 0 | D30: 0 | E30: 0 | F30: 0 | G30: 400 | H30: 50000 | I30: 13950 | J30: 13884 | K30: =1 -> 1
B32: Referral fee by category (販売手数料, tax-excluded %)
B33: Category (English) | C33: カテゴリー | D33: <=¥750 | E33: ¥750-1,500 | F33: >¥1,500
B34: Beauty, health & personal care | C34: ビューティ・ヘルス・パーソナルケア | D34: 0.05 | E34: 0.084 | F34: 0.104
B35: Drugstore | C35: ドラッグストア | D35: 0.05 | E35: 0.084 | F35: 0.104
B36: Food & beverage | C36: 食品・飲料 | D36: 0.05 | E36: 0.084 | F36: 0.104
B37: Baby & maternity | C37: ベビー・マタニティ | D37: 0.05 | E37: 0.084 | F37: 0.154
B38: Pet supplies | C38: ペット用品 | D38: 0.05 | E38: 0.084 | F38: 0.154
B39: Sports & outdoors | C39: スポーツ・アウトドア | D39: 0.05 | E39: 0.104 | F39: 0.104
B40: Home & kitchen | C40: ホーム・キッチン | D40: 0.05 | E40: 0.154 | F40: 0.154
B41: Home & kitchen appliances | C41: ホーム・キッチン家電 | D41: 0.05 | E41: 0.104 | F41: 0.104
B42: Toys & hobbies | C42: おもちゃ・ホビー | D42: 0.05 | E42: 0.104 | F42: 0.104
B43: Stationery & office | C43: 文房具・オフィス用品 | D43: 0.05 | E43: 0.154 | F43: 0.154
B44: Gardening | C44: ガーデニング・園芸用品 | D44: 0.05 | E44: 0.154 | F44: 0.154
B45: Everything else (default) | C45: その他のカテゴリー | D45: 0.05 | E45: 0.154 | F45: 0.154

Sheet PL Monthly
B2: Made for Doraemon | N2: ="Currency: "&a_currency&" · switch on the Dashboard" -> Currency: JPY · switch on the Dashboard
B4: P&L — 36 months
B5: Live formulas; costs negative; sales start Aug (launch month drives seasonality). Flip the scenario on the Assumptions sheet and everything recalculates.
B7: P&L line | C7: M1 · Aug | D7: M2 · Sep | E7: M3 · Oct | F7: M4 · Nov | G7: M5 · Dec | H7: M6 · Jan | I7: M7 · Feb | J7: M8 · Mar | K7: M9 · Apr | L7: M10 · May | M7: M11 · Jun | N7: M12 · Jul | O7: M13 · Aug | P7: M14 · Sep | Q7: M15 · Oct | R7: M16 · Nov | S7: M17 · Dec | T7: M18 · Jan | U7: M19 · Feb | V7: M20 · Mar | W7: M21 · Apr | X7: M22 · May | Y7: M23 · Jun | Z7: M24 · Jul | AA7: M25 · Aug | AB7: M26 · Sep | AC7: M27 · Oct | AD7: M28 · Nov | AE7: M29 · Dec | AF7: M30 · Jan | AG7: M31 · Feb | AH7: M32 · Mar | AI7: M33 · Apr | AJ7: M34 · May | AK7: M35 · Jun | AL7: M36 · Jul
B8: · demand (whole niche, units) | C8: =a_units_360d/12*INDEX(a_seasonality,8)*1 -> 1500 | D8: =a_units_360d/12*INDEX(a_seasonality,9)*1 -> 1500 | E8: =a_units_360d/12*INDEX(a_seasonality,10)*1 -> 1500 | F8: =a_units_360d/12*INDEX(a_seasonality,11)*1 -> 1500 | G8: =a_units_360d/12*INDEX(a_seasonality,12)*1 -> 1500 | H8: =a_units_360d/12*INDEX(a_seasonality,1)*1 -> 1500 | I8: =a_units_360d/12*INDEX(a_seasonality,2)*1 -> 1500 | J8: =a_units_360d/12*INDEX(a_seasonality,3)*1 -> 1500 | K8: =a_units_360d/12*INDEX(a_seasonality,4)*1 -> 1500 | L8: =a_units_360d/12*INDEX(a_seasonality,5)*1 -> 1500 | M8: =a_units_360d/12*INDEX(a_seasonality,6)*1 -> 1500 | N8: =a_units_360d/12*INDEX(a_seasonality,7)*1 -> 1500 | O8: =a_units_360d/12*INDEX(a_seasonality,8)*(1+a_demand_growth_y2) -> 1815 | P8: =a_units_360d/12*INDEX(a_seasonality,9)*(1+a_demand_growth_y2) -> 1815 | Q8: =a_units_360d/12*INDEX(a_seasonality,10)*(1+a_demand_growth_y2) -> 1815 | R8: =a_units_360d/12*INDEX(a_seasonality,11)*(1+a_demand_growth_y2) -> 1815 | S8: =a_units_360d/12*INDEX(a_seasonality,12)*(1+a_demand_growth_y2) -> 1815 | T8: =a_units_360d/12*INDEX(a_seasonality,1)*(1+a_demand_growth_y2) -> 1815 | U8: =a_units_360d/12*INDEX(a_seasonality,2)*(1+a_demand_growth_y2) -> 1815 | V8: =a_units_360d/12*INDEX(a_seasonality,3)*(1+a_demand_growth_y2) -> 1815 | W8: =a_units_360d/12*INDEX(a_seasonality,4)*(1+a_demand_growth_y2) -> 1815 | X8: =a_units_360d/12*INDEX(a_seasonality,5)*(1+a_demand_growth_y2) -> 1815 | Y8: =a_units_360d/12*INDEX(a_seasonality,6)*(1+a_demand_growth_y2) -> 1815 | Z8: =a_units_360d/12*INDEX(a_seasonality,7)*(1+a_demand_growth_y2) -> 1815 | AA8: =a_units_360d/12*INDEX(a_seasonality,8)*(1+a_demand_growth_y2)*(1+a_demand_growth_y3) -> 2196.15 | AB8: =a_units_360d/12*INDEX(a_seasonality,9)*(1+a_demand_growth_y2)*(1+a_demand_growth_y3) -> 2196.15 | AC8: =a_units_360d/12*INDEX(a_seasonality,10)*(1+a_demand_growth_y2)*(1+a_demand_growth_y3) -> 2196.15 | AD8: =a_units_360d/12*INDEX(a_seasonality,11)*(1+a_demand_growth_y2)*(1+a_demand_growth_y3) -> 2196.15 | AE8: =a_units_360d/12*INDEX(a_seasonality,12)*(1+a_demand_growth_y2)*(1+a_demand_growth_y3) -> 2196.15 | AF8: =a_units_360d/12*INDEX(a_seasonality,1)*(1+a_demand_growth_y2)*(1+a_demand_growth_y3) -> 2196.15 | AG8: =a_units_360d/12*INDEX(a_seasonality,2)*(1+a_demand_growth_y2)*(1+a_demand_growth_y3) -> 2196.15 | AH8: =a_units_360d/12*INDEX(a_seasonality,3)*(1+a_demand_growth_y2)*(1+a_demand_growth_y3) -> 2196.15 | AI8: =a_units_360d/12*INDEX(a_seasonality,4)*(1+a_demand_growth_y2)*(1+a_demand_growth_y3) -> 2196.15 | AJ8: =a_units_360d/12*INDEX(a_seasonality,5)*(1+a_demand_growth_y2)*(1+a_demand_growth_y3) -> 2196.15 | AK8: =a_units_360d/12*INDEX(a_seasonality,6)*(1+a_demand_growth_y2)*(1+a_demand_growth_y3) -> 2196.15 | AL8: =a_units_360d/12*INDEX(a_seasonality,7)*(1+a_demand_growth_y2)*(1+a_demand_growth_y3) -> 2196.15
B9: · your market share | C9: =MIN(a_act_target_share,a_share_cap)*MIN(1,1/a_ramp_months) -> 0.0055555556 | D9: =MIN(a_act_target_share,a_share_cap)*MIN(1,2/a_ramp_months) -> 0.011111111 | E9: =MIN(a_act_target_share,a_share_cap)*MIN(1,3/a_ramp_months) -> 0.016666667 | F9: =MIN(a_act_target_share,a_share_cap)*MIN(1,4/a_ramp_months) -> 0.022222222 | G9: =MIN(a_act_target_share,a_share_cap)*MIN(1,5/a_ramp_months) -> 0.027777778 | H9: =MIN(a_act_target_share,a_share_cap)*MIN(1,6/a_ramp_months) -> 0.033333333 | I9: =MIN(a_act_target_share,a_share_cap)*MIN(1,7/a_ramp_months) -> 0.038888889 | J9: =MIN(a_act_target_share,a_share_cap)*MIN(1,8/a_ramp_months) -> 0.044444444 | K9: =MIN(a_act_target_share,a_share_cap)*MIN(1,9/a_ramp_months) -> 0.05 | L9: =MIN(a_act_target_share,a_share_cap)*MIN(1,10/a_ramp_months) -> 0.05 | M9: =MIN(a_act_target_share,a_share_cap)*MIN(1,11/a_ramp_months) -> 0.05 | N9: =MIN(a_act_target_share,a_share_cap)*MIN(1,12/a_ramp_months) -> 0.05 | O9: =MIN(a_act_target_share,a_share_cap)*MIN(1,13/a_ramp_months) -> 0.05 | P9: =MIN(a_act_target_share,a_share_cap)*MIN(1,14/a_ramp_months) -> 0.05 | Q9: =MIN(a_act_target_share,a_share_cap)*MIN(1,15/a_ramp_months) -> 0.05 | R9: =MIN(a_act_target_share,a_share_cap)*MIN(1,16/a_ramp_months) -> 0.05 | S9: =MIN(a_act_target_share,a_share_cap)*MIN(1,17/a_ramp_months) -> 0.05 | T9: =MIN(a_act_target_share,a_share_cap)*MIN(1,18/a_ramp_months) -> 0.05 | U9: =MIN(a_act_target_share,a_share_cap)*MIN(1,19/a_ramp_months) -> 0.05 | V9: =MIN(a_act_target_share,a_share_cap)*MIN(1,20/a_ramp_months) -> 0.05 | W9: =MIN(a_act_target_share,a_share_cap)*MIN(1,21/a_ramp_months) -> 0.05 | X9: =MIN(a_act_target_share,a_share_cap)*MIN(1,22/a_ramp_months) -> 0.05 | Y9: =MIN(a_act_target_share,a_share_cap)*MIN(1,23/a_ramp_months) -> 0.05 | Z9: =MIN(a_act_target_share,a_share_cap)*MIN(1,24/a_ramp_months) -> 0.05 | AA9: =MIN(a_act_target_share,a_share_cap)*MIN(1,25/a_ramp_months) -> 0.05 | AB9: =MIN(a_act_target_share,a_share_cap)*MIN(1,26/a_ramp_months) -> 0.05 | AC9: =MIN(a_act_target_share,a_share_cap)*MIN(1,27/a_ramp_months) -> 0.05 | AD9: =MIN(a_act_target_share,a_share_cap)*MIN(1,28/a_ramp_months) -> 0.05 | AE9: =MIN(a_act_target_share,a_share_cap)*MIN(1,29/a_ramp_months) -> 0.05 | AF9: =MIN(a_act_target_share,a_share_cap)*MIN(1,30/a_ramp_months) -> 0.05 | AG9: =MIN(a_act_target_share,a_share_cap)*MIN(1,31/a_ramp_months) -> 0.05 | AH9: =MIN(a_act_target_share,a_share_cap)*MIN(1,32/a_ramp_months) -> 0.05 | AI9: =MIN(a_act_target_share,a_share_cap)*MIN(1,33/a_ramp_months) -> 0.05 | AJ9: =MIN(a_act_target_share,a_share_cap)*MIN(1,34/a_ramp_months) -> 0.05 | AK9: =MIN(a_act_target_share,a_share_cap)*MIN(1,35/a_ramp_months) -> 0.05 | AL9: =MIN(a_act_target_share,a_share_cap)*MIN(1,36/a_ramp_months) -> 0.05
B10: Units sold | C10: =C8*C9 -> 8.3333333 | D10: =D8*D9 -> 16.666667 | E10: =E8*E9 -> 25 | F10: =F8*F9 -> 33.333333 | G10: =G8*G9 -> 41.666667 | H10: =H8*H9 -> 50 | I10: =I8*I9 -> 58.333333 | J10: =J8*J9 -> 66.666667 | ... AL10: =AL8*AL9 -> 109.8075
B11: ASP (tax-incl) | C11: =a_act_asp_jpy/a_cur_div -> 3500 | D11: =a_act_asp_jpy/a_cur_div -> 3500 | E11: =a_act_asp_jpy/a_cur_div -> 3500 | F11: =a_act_asp_jpy/a_cur_div -> 3500 | G11: =a_act_asp_jpy/a_cur_div -> 3500 | H11: =a_act_asp_jpy/a_cur_div -> 3500 | I11: =a_act_asp_jpy/a_cur_div -> 3500 | J11: =a_act_asp_jpy/a_cur_div -> 3500 | ... AL11: =a_act_asp_jpy/a_cur_div -> 3500
B12: Gross sales | C12: =C10*C11 -> 29166.667 | D12: =D10*D11 -> 58333.333 | E12: =E10*E11 -> 87500 | F12: =F10*F11 -> 116666.67 | G12: =G10*G11 -> 145833.33 | H12: =H10*H11 -> 175000 | I12: =I10*I11 -> 204166.67 | J12: =J10*J11 -> 233333.33 | ... AL12: =AL10*AL11 -> 384326.25
B13: Output JCT | C13: =-C12*a_jct_rate_output/(1+a_jct_rate_output) -> -2651.5152 | D13: =-D12*a_jct_rate_output/(1+a_jct_rate_output) -> -5303.0303 | E13: =-E12*a_jct_rate_output/(1+a_jct_rate_output) -> -7954.5455 | F13: =-F12*a_jct_rate_output/(1+a_jct_rate_output) -> -10606.061 | G13: =-G12*a_jct_rate_output/(1+a_jct_rate_output) -> -13257.576 | H13: =-H12*a_jct_rate_output/(1+a_jct_rate_output) -> -15909.091 | I13: =-I12*a_jct_rate_output/(1+a_jct_rate_output) -> -18560.606 | J13: =-J12*a_jct_rate_output/(1+a_jct_rate_output) -> -21212.121 | ... AL13: =-AL12*a_jct_rate_output/(1+a_jct_rate_output) -> -34938.75
B14: Amazon Points | C14: =-C12*a_points_rate -> -291.66667 | D14: =-D12*a_points_rate -> -583.33333 | E14: =-E12*a_points_rate -> -875 | F14: =-F12*a_points_rate -> -1166.6667 | G14: =-G12*a_points_rate -> -1458.3333 | H14: =-H12*a_points_rate -> -1750 | I14: =-I12*a_points_rate -> -2041.6667 | J14: =-J12*a_points_rate -> -2333.3333 | ... AL14: =-AL12*a_points_rate -> -3843.2625
B15: Promotions & deals | C15: =-C12*IF(1<=a_promo_launch_months,a_promo_rate_launch,a_promo_rate_steady)-a_promo_fixed_jpy/a_cur_div -> -2333.3333 | D15: =-D12*IF(2<=a_promo_launch_months,a_promo_rate_launch,a_promo_rate_steady)-a_promo_fixed_jpy/a_cur_div -> -4666.6667 | E15: =-E12*IF(3<=a_promo_launch_months,a_promo_rate_launch,a_promo_rate_steady)-a_promo_fixed_jpy/a_cur_div -> -7000 | F15: =-F12*IF(4<=a_promo_launch_months,a_promo_rate_launch,a_promo_rate_steady)-a_promo_fixed_jpy/a_cur_div -> -2333.3333 | G15: =-G12*IF(5<=a_promo_launch_months,a_promo_rate_launch,a_promo_rate_steady)-a_promo_fixed_jpy/a_cur_div -> -2916.6667 | H15: =-H12*IF(6<=a_promo_launch_months,a_promo_rate_launch,a_promo_rate_steady)-a_promo_fixed_jpy/a_cur_div -> -3500 | I15: =-I12*IF(7<=a_promo_launch_months,a_promo_rate_launch,a_promo_rate_steady)-a_promo_fixed_jpy/a_cur_div -> -4083.3333 | J15: =-J12*IF(8<=a_promo_launch_months,a_promo_rate_launch,a_promo_rate_steady)-a_promo_fixed_jpy/a_cur_div -> -4666.6667 | K15: =-K12*IF(9<=a_promo_launch_months,a_promo_rate_launch,a_promo_rate_steady)-a_promo_fixed_jpy/a_cur_div -> -5250 | L15: =-L12*IF(10<=a_promo_launch_months,a_promo_rate_launch,a_promo_rate_steady)-a_promo_fixed_jpy/a_cur_div -> -5250 | M15: =-M12*IF(11<=a_promo_launch_months,a_promo_rate_launch,a_promo_rate_steady)-a_promo_fixed_jpy/a_cur_div -> -5250 | N15: =-N12*IF(12<=a_promo_launch_months,a_promo_rate_launch,a_promo_rate_steady)-a_promo_fixed_jpy/a_cur_div -> -5250 | O15: =-O12*IF(13<=a_promo_launch_months,a_promo_rate_launch,a_promo_rate_steady)-a_promo_fixed_jpy/a_cur_div -> -6352.5 | P15: =-P12*IF(14<=a_promo_launch_months,a_promo_rate_launch,a_promo_rate_steady)-a_promo_fixed_jpy/a_cur_div -> -6352.5 | Q15: =-Q12*IF(15<=a_promo_launch_months,a_promo_rate_launch,a_promo_rate_steady)-a_promo_fixed_jpy/a_cur_div -> -6352.5 | R15: =-R12*IF(16<=a_promo_launch_months,a_promo_rate_launch,a_promo_rate_steady)-a_promo_fixed_jpy/a_cur_div -> -6352.5 | S15: =-S12*IF(17<=a_promo_launch_months,a_promo_rate_launch,a_promo_rate_steady)-a_promo_fixed_jpy/a_cur_div -> -6352.5 | T15: =-T12*IF(18<=a_promo_launch_months,a_promo_rate_launch,a_promo_rate_steady)-a_promo_fixed_jpy/a_cur_div -> -6352.5 | U15: =-U12*IF(19<=a_promo_launch_months,a_promo_rate_launch,a_promo_rate_steady)-a_promo_fixed_jpy/a_cur_div -> -6352.5 | V15: =-V12*IF(20<=a_promo_launch_months,a_promo_rate_launch,a_promo_rate_steady)-a_promo_fixed_jpy/a_cur_div -> -6352.5 | W15: =-W12*IF(21<=a_promo_launch_months,a_promo_rate_launch,a_promo_rate_steady)-a_promo_fixed_jpy/a_cur_div -> -6352.5 | X15: =-X12*IF(22<=a_promo_launch_months,a_promo_rate_launch,a_promo_rate_steady)-a_promo_fixed_jpy/a_cur_div -> -6352.5 | Y15: =-Y12*IF(23<=a_promo_launch_months,a_promo_rate_launch,a_promo_rate_steady)-a_promo_fixed_jpy/a_cur_div -> -6352.5 | Z15: =-Z12*IF(24<=a_promo_launch_months,a_promo_rate_launch,a_promo_rate_steady)-a_promo_fixed_jpy/a_cur_div -> -6352.5 | AA15: =-AA12*IF(25<=a_promo_launch_months,a_promo_rate_launch,a_promo_rate_steady)-a_promo_fixed_jpy/a_cur_div -> -7686.525 | AB15: =-AB12*IF(26<=a_promo_launch_months,a_promo_rate_launch,a_promo_rate_steady)-a_promo_fixed_jpy/a_cur_div -> -7686.525 | AC15: =-AC12*IF(27<=a_promo_launch_months,a_promo_rate_launch,a_promo_rate_steady)-a_promo_fixed_jpy/a_cur_div -> -7686.525 | AD15: =-AD12*IF(28<=a_promo_launch_months,a_promo_rate_launch,a_promo_rate_steady)-a_promo_fixed_jpy/a_cur_div -> -7686.525 | AE15: =-AE12*IF(29<=a_promo_launch_months,a_promo_rate_launch,a_promo_rate_steady)-a_promo_fixed_jpy/a_cur_div -> -7686.525 | AF15: =-AF12*IF(30<=a_promo_launch_months,a_promo_rate_launch,a_promo_rate_steady)-a_promo_fixed_jpy/a_cur_div -> -7686.525 | AG15: =-AG12*IF(31<=a_promo_launch_months,a_promo_rate_launch,a_promo_rate_steady)-a_promo_fixed_jpy/a_cur_div -> -7686.525 | AH15: =-AH12*IF(32<=a_promo_launch_months,a_promo_rate_launch,a_promo_rate_steady)-a_promo_fixed_jpy/a_cur_div -> -7686.525 | AI15: =-AI12*IF(33<=a_promo_launch_months,a_promo_rate_launch,a_promo_rate_steady)-a_promo_fixed_jpy/a_cur_div -> -7686.525 | AJ15: =-AJ12*IF(34<=a_promo_launch_months,a_promo_rate_launch,a_promo_rate_steady)-a_promo_fixed_jpy/a_cur_div -> -7686.525 | AK15: =-AK12*IF(35<=a_promo_launch_months,a_promo_rate_launch,a_promo_rate_steady)-a_promo_fixed_jpy/a_cur_div -> -7686.525 | AL15: =-AL12*IF(36<=a_promo_launch_months,a_promo_rate_launch,a_promo_rate_steady)-a_promo_fixed_jpy/a_cur_div -> -7686.525
B16: Returns | C16: =-a_return_rate*C12 -> -583.33333 | D16: =-a_return_rate*D12 -> -1166.6667 | E16: =-a_return_rate*E12 -> -1750 | F16: =-a_return_rate*F12 -> -2333.3333 | G16: =-a_return_rate*G12 -> -2916.6667 | H16: =-a_return_rate*H12 -> -3500 | I16: =-a_return_rate*I12 -> -4083.3333 | J16: =-a_return_rate*J12 -> -4666.6667 | ... AL16: =-a_return_rate*AL12 -> -7686.525
B17: Net revenue | C17: =C12+C13+C14+C15+C16 -> 23306.818 | D17: =D12+D13+D14+D15+D16 -> 46613.636 | E17: =E12+E13+E14+E15+E16 -> 69920.455 | F17: =F12+F13+F14+F15+F16 -> 100227.27 | G17: =G12+G13+G14+G15+G16 -> 125284.09 | H17: =H12+H13+H14+H15+H16 -> 150340.91 | I17: =I12+I13+I14+I15+I16 -> 175397.73 | J17: =J12+J13+J14+J15+J16 -> 200454.55 | ... AL17: =AL12+AL13+AL14+AL15+AL16 -> 330171.19
B18: Unit procurement cost | C18: =-C10*a_act_cogs_pu/a_cur_div -> -13125 | D18: =-D10*a_act_cogs_pu/a_cur_div -> -26250 | E18: =-E10*a_act_cogs_pu/a_cur_div -> -39375 | F18: =-F10*a_act_cogs_pu/a_cur_div -> -52500 | G18: =-G10*a_act_cogs_pu/a_cur_div -> -65625 | H18: =-H10*a_act_cogs_pu/a_cur_div -> -78750 | I18: =-I10*a_act_cogs_pu/a_cur_div -> -91875 | J18: =-J10*a_act_cogs_pu/a_cur_div -> -105000 | ... AL18: =-AL10*a_act_cogs_pu/a_cur_div -> -172946.81
B19: Domestic logistics to FBA | C19: =-C10*a_logistics_jpy_per_unit/a_cur_div -> -416.66667 | D19: =-D10*a_logistics_jpy_per_unit/a_cur_div -> -833.33333 | E19: =-E10*a_logistics_jpy_per_unit/a_cur_div -> -1250 | F19: =-F10*a_logistics_jpy_per_unit/a_cur_div -> -1666.6667 | G19: =-G10*a_logistics_jpy_per_unit/a_cur_div -> -2083.3333 | H19: =-H10*a_logistics_jpy_per_unit/a_cur_div -> -2500 | I19: =-I10*a_logistics_jpy_per_unit/a_cur_div -> -2916.6667 | J19: =-J10*a_logistics_jpy_per_unit/a_cur_div -> -3333.3333 | ... AL19: =-AL10*a_logistics_jpy_per_unit/a_cur_div -> -5490.375
B20: Inspection / QC | C20: =-C10*a_inspection_jpy_per_unit/a_cur_div -> 0 | D20: =-D10*a_inspection_jpy_per_unit/a_cur_div -> 0 | E20: =-E10*a_inspection_jpy_per_unit/a_cur_div -> 0 | F20: =-F10*a_inspection_jpy_per_unit/a_cur_div -> 0 | G20: =-G10*a_inspection_jpy_per_unit/a_cur_div -> 0 | H20: =-H10*a_inspection_jpy_per_unit/a_cur_div -> 0 | I20: =-I10*a_inspection_jpy_per_unit/a_cur_div -> 0 | J20: =-J10*a_inspection_jpy_per_unit/a_cur_div -> 0 | ... AL20: =-AL10*a_inspection_jpy_per_unit/a_cur_div -> 0
B21: Shrinkage & write-offs | C21: =a_shrinkage_rate*(C18+C19+C20)+C10*a_return_rate*a_return_salvage_rate*a_act_basis_pu/a_cur_div -> -135.41667 | D21: =a_shrinkage_rate*(D18+D19+D20)+D10*a_return_rate*a_return_salvage_rate*a_act_basis_pu/a_cur_div -> -270.83333 | E21: =a_shrinkage_rate*(E18+E19+E20)+E10*a_return_rate*a_return_salvage_rate*a_act_basis_pu/a_cur_div -> -406.25 | F21: =a_shrinkage_rate*(F18+F19+F20)+F10*a_return_rate*a_return_salvage_rate*a_act_basis_pu/a_cur_div -> -541.66667 | G21: =a_shrinkage_rate*(G18+G19+G20)+G10*a_return_rate*a_return_salvage_rate*a_act_basis_pu/a_cur_div -> -677.08333 | H21: =a_shrinkage_rate*(H18+H19+H20)+H10*a_return_rate*a_return_salvage_rate*a_act_basis_pu/a_cur_div -> -812.5 | I21: =a_shrinkage_rate*(I18+I19+I20)+I10*a_return_rate*a_return_salvage_rate*a_act_basis_pu/a_cur_div -> -947.91667 | J21: =a_shrinkage_rate*(J18+J19+J20)+J10*a_return_rate*a_return_salvage_rate*a_act_basis_pu/a_cur_div -> -1083.3333 | ... AL21: =a_shrinkage_rate*(AL18+AL19+AL20)+AL10*a_return_rate*a_return_salvage_rate*a_act_basis_pu/a_cur_div -> -1784.3719
B22: Gross profit | C22: =C17+C18+C19+C20+C21 -> 9629.7348 | D22: =D17+D18+D19+D20+D21 -> 19259.47 | E22: =E17+E18+E19+E20+E21 -> 28889.205 | F22: =F17+F18+F19+F20+F21 -> 45518.939 | G22: =G17+G18+G19+G20+G21 -> 56898.674 | H22: =H17+H18+H19+H20+H21 -> 68278.409 | I22: =I17+I18+I19+I20+I21 -> 79658.144 | J22: =J17+J18+J19+J20+J21 -> 91037.879 | ... AL22: =AL17+AL18+AL19+AL20+AL21 -> 149949.63
B23: Referral fee | C23: =-C10*a_act_referral_pu/a_cur_div -> -3033.3333 | D23: =-D10*a_act_referral_pu/a_cur_div -> -6066.6667 | E23: =-E10*a_act_referral_pu/a_cur_div -> -9100 | F23: =-F10*a_act_referral_pu/a_cur_div -> -12133.333 | G23: =-G10*a_act_referral_pu/a_cur_div -> -15166.667 | H23: =-H10*a_act_referral_pu/a_cur_div -> -18200 | I23: =-I10*a_act_referral_pu/a_cur_div -> -21233.333 | J23: =-J10*a_act_referral_pu/a_cur_div -> -24266.667 | ... AL23: =-AL10*a_act_referral_pu/a_cur_div -> -39969.93
B24: FBA fulfillment | C24: =-C10*a_fba_fee_net/a_cur_div -> -3143.9394 | D24: =-D10*a_fba_fee_net/a_cur_div -> -6287.8788 | E24: =-E10*a_fba_fee_net/a_cur_div -> -9431.8182 | F24: =-F10*a_fba_fee_net/a_cur_div -> -12575.758 | G24: =-G10*a_fba_fee_net/a_cur_div -> -15719.697 | H24: =-H10*a_fba_fee_net/a_cur_div -> -18863.636 | I24: =-I10*a_fba_fee_net/a_cur_div -> -22007.576 | J24: =-J10*a_fba_fee_net/a_cur_div -> -25151.515 | ... AL24: =-AL10*a_fba_fee_net/a_cur_div -> -41427.375
B25: Storage | C25: =-(('Investment and Cash'!E8+'Investment and Cash'!E11)/2)*a_unit_vol_1000cm3*a_storage_rate_jan_sep/a_cur_div -> -264.708 | D25: =-(('Investment and Cash'!F8+'Investment and Cash'!F11)/2)*a_unit_vol_1000cm3*a_storage_rate_jan_sep/a_cur_div -> -222.912 | E25: =-(('Investment and Cash'!G8+'Investment and Cash'!G11)/2)*a_unit_vol_1000cm3*a_storage_rate_oct_dec/a_cur_div -> -272.349 | F25: =-(('Investment and Cash'!H8+'Investment and Cash'!H11)/2)*a_unit_vol_1000cm3*a_storage_rate_oct_dec/a_cur_div -> -346.626 | G25: =-(('Investment and Cash'!I8+'Investment and Cash'!I11)/2)*a_unit_vol_1000cm3*a_storage_rate_oct_dec/a_cur_div -> -420.903 | H25: =-(('Investment and Cash'!J8+'Investment and Cash'!J11)/2)*a_unit_vol_1000cm3*a_storage_rate_jan_sep/a_cur_div -> -278.64 | I25: =-(('Investment and Cash'!K8+'Investment and Cash'!K11)/2)*a_unit_vol_1000cm3*a_storage_rate_jan_sep/a_cur_div -> -320.436 | J25: =-(('Investment and Cash'!L8+'Investment and Cash'!L11)/2)*a_unit_vol_1000cm3*a_storage_rate_jan_sep/a_cur_div -> -362.232 | K25: =-(('Investment and Cash'!M8+'Investment and Cash'!M11)/2)*a_unit_vol_1000cm3*a_storage_rate_jan_sep/a_cur_div -> -376.164 | L25: =-(('Investment and Cash'!N8+'Investment and Cash'!N11)/2)*a_unit_vol_1000cm3*a_storage_rate_jan_sep/a_cur_div -> -376.164 | M25: =-(('Investment and Cash'!O8+'Investment and Cash'!O11)/2)*a_unit_vol_1000cm3*a_storage_rate_jan_sep/a_cur_div -> -376.164 | N25: =-(('Investment and Cash'!P8+'Investment and Cash'!P11)/2)*a_unit_vol_1000cm3*a_storage_rate_jan_sep/a_cur_div -> -428.82696 | O25: =-(('Investment and Cash'!Q8+'Investment and Cash'!Q11)/2)*a_unit_vol_1000cm3*a_storage_rate_jan_sep/a_cur_div -> -455.15844 | P25: =-(('Investment and Cash'!R8+'Investment and Cash'!R11)/2)*a_unit_vol_1000cm3*a_storage_rate_jan_sep/a_cur_div -> -455.15844 | Q25: =-(('Investment and Cash'!S8+'Investment and Cash'!S11)/2)*a_unit_vol_1000cm3*a_storage_rate_oct_dec/a_cur_div -> -808.87653 | R25: =-(('Investment and Cash'!T8+'Investment and Cash'!T11)/2)*a_unit_vol_1000cm3*a_storage_rate_oct_dec/a_cur_div -> -808.87653 | S25: =-(('Investment and Cash'!U8+'Investment and Cash'!U11)/2)*a_unit_vol_1000cm3*a_storage_rate_oct_dec/a_cur_div -> -808.87653 | T25: =-(('Investment and Cash'!V8+'Investment and Cash'!V11)/2)*a_unit_vol_1000cm3*a_storage_rate_jan_sep/a_cur_div -> -455.15844 | U25: =-(('Investment and Cash'!W8+'Investment and Cash'!W11)/2)*a_unit_vol_1000cm3*a_storage_rate_jan_sep/a_cur_div -> -455.15844 | V25: =-(('Investment and Cash'!X8+'Investment and Cash'!X11)/2)*a_unit_vol_1000cm3*a_storage_rate_jan_sep/a_cur_div -> -455.15844 | W25: =-(('Investment and Cash'!Y8+'Investment and Cash'!Y11)/2)*a_unit_vol_1000cm3*a_storage_rate_jan_sep/a_cur_div -> -455.15844 | X25: =-(('Investment and Cash'!Z8+'Investment and Cash'!Z11)/2)*a_unit_vol_1000cm3*a_storage_rate_jan_sep/a_cur_div -> -455.15844 | Y25: =-(('Investment and Cash'!AA8+'Investment and Cash'!AA11)/2)*a_unit_vol_1000cm3*a_storage_rate_jan_sep/a_cur_div -> -455.15844 | Z25: =-(('Investment and Cash'!AB8+'Investment and Cash'!AB11)/2)*a_unit_vol_1000cm3*a_storage_rate_jan_sep/a_cur_div -> -518.88062 | AA25: =-(('Investment and Cash'!AC8+'Investment and Cash'!AC11)/2)*a_unit_vol_1000cm3*a_storage_rate_jan_sep/a_cur_div -> -550.74171 | AB25: =-(('Investment and Cash'!AD8+'Investment and Cash'!AD11)/2)*a_unit_vol_1000cm3*a_storage_rate_jan_sep/a_cur_div -> -550.74171 | AC25: =-(('Investment and Cash'!AE8+'Investment and Cash'!AE11)/2)*a_unit_vol_1000cm3*a_storage_rate_oct_dec/a_cur_div -> -978.7406 | AD25: =-(('Investment and Cash'!AF8+'Investment and Cash'!AF11)/2)*a_unit_vol_1000cm3*a_storage_rate_oct_dec/a_cur_div -> -978.7406 | AE25: =-(('Investment and Cash'!AG8+'Investment and Cash'!AG11)/2)*a_unit_vol_1000cm3*a_storage_rate_oct_dec/a_cur_div -> -978.7406 | AF25: =-(('Investment and Cash'!AH8+'Investment and Cash'!AH11)/2)*a_unit_vol_1000cm3*a_storage_rate_jan_sep/a_cur_div -> -550.74171 | AG25: =-(('Investment and Cash'!AI8+'Investment and Cash'!AI11)/2)*a_unit_vol_1000cm3*a_storage_rate_jan_sep/a_cur_div -> -550.74171 | AH25: =-(('Investment and Cash'!AJ8+'Investment and Cash'!AJ11)/2)*a_unit_vol_1000cm3*a_storage_rate_jan_sep/a_cur_div -> -550.74171 | AI25: =-(('Investment and Cash'!AK8+'Investment and Cash'!AK11)/2)*a_unit_vol_1000cm3*a_storage_rate_jan_sep/a_cur_div -> -550.74171 | AJ25: =-(('Investment and Cash'!AL8+'Investment and Cash'!AL11)/2)*a_unit_vol_1000cm3*a_storage_rate_jan_sep/a_cur_div -> -550.74171 | AK25: =-(('Investment and Cash'!AM8+'Investment and Cash'!AM11)/2)*a_unit_vol_1000cm3*a_storage_rate_jan_sep/a_cur_div -> -550.74171 | AL25: =-(('Investment and Cash'!AN8+'Investment and Cash'!AN11)/2)*a_unit_vol_1000cm3*a_storage_rate_jan_sep/a_cur_div -> -183.58057
B26: Long-term storage | C26: =INDEX('PL Monthly'!C41:C43,MATCH(a_scenario,a_scn_names,0))/a_cur_div -> 0 | D26: =INDEX('PL Monthly'!D41:D43,MATCH(a_scenario,a_scn_names,0))/a_cur_div -> 0 | E26: =INDEX('PL Monthly'!E41:E43,MATCH(a_scenario,a_scn_names,0))/a_cur_div -> 0 | F26: =INDEX('PL Monthly'!F41:F43,MATCH(a_scenario,a_scn_names,0))/a_cur_div -> 0 | G26: =INDEX('PL Monthly'!G41:G43,MATCH(a_scenario,a_scn_names,0))/a_cur_div -> 0 | H26: =INDEX('PL Monthly'!H41:H43,MATCH(a_scenario,a_scn_names,0))/a_cur_div -> 0 | I26: =INDEX('PL Monthly'!I41:I43,MATCH(a_scenario,a_scn_names,0))/a_cur_div -> 0 | J26: =INDEX('PL Monthly'!J41:J43,MATCH(a_scenario,a_scn_names,0))/a_cur_div -> 0 | ... AL26: =INDEX('PL Monthly'!AL41:AL43,MATCH(a_scenario,a_scn_names,0))/a_cur_div -> 0
B27: Referral refund on returns | C27: =C10*a_return_rate*(a_act_referral_pu-a_act_refund_admin_pu)/a_cur_div -> 48.533333 | D27: =D10*a_return_rate*(a_act_referral_pu-a_act_refund_admin_pu)/a_cur_div -> 97.066667 | E27: =E10*a_return_rate*(a_act_referral_pu-a_act_refund_admin_pu)/a_cur_div -> 145.6 | F27: =F10*a_return_rate*(a_act_referral_pu-a_act_refund_admin_pu)/a_cur_div -> 194.13333 | G27: =G10*a_return_rate*(a_act_referral_pu-a_act_refund_admin_pu)/a_cur_div -> 242.66667 | H27: =H10*a_return_rate*(a_act_referral_pu-a_act_refund_admin_pu)/a_cur_div -> 291.2 | I27: =I10*a_return_rate*(a_act_referral_pu-a_act_refund_admin_pu)/a_cur_div -> 339.73333 | J27: =J10*a_return_rate*(a_act_referral_pu-a_act_refund_admin_pu)/a_cur_div -> 388.26667 | ... AL27: =AL10*a_return_rate*(a_act_referral_pu-a_act_refund_admin_pu)/a_cur_div -> 639.51888
B28: Contribution margin | C28: =C22+C23+C24+C25+C26+C27 -> 3236.2875 | D28: =D22+D23+D24+D25+D26+D27 -> 6779.0789 | E28: =E22+E23+E24+E25+E26+E27 -> 10230.637 | F28: =F22+F23+F24+F25+F26+F27 -> 20657.356 | G28: =G22+G23+G24+G25+G26+G27 -> 25834.074 | H28: =H22+H23+H24+H25+H26+H27 -> 31227.333 | I28: =I22+I23+I24+I25+I26+I27 -> 36436.532 | J28: =J22+J23+J24+J25+J26+J27 -> 41645.732 | ... AL28: =AL22+AL23+AL24+AL25+AL26+AL27 -> 69008.261
B29: PPC advertising | C29: =-MAX(C12*MAX(0,a_act_tacos_y1_start+(a_act_tacos_y1_end-a_act_tacos_y1_start)*(1-1)/11),a_ppc_launch_monthly_min_jpy/a_cur_div) -> -30000 | D29: =-MAX(D12*MAX(0,a_act_tacos_y1_start+(a_act_tacos_y1_end-a_act_tacos_y1_start)*(2-1)/11),a_ppc_launch_monthly_min_jpy/a_cur_div) -> -30000 | E29: =-MAX(E12*MAX(0,a_act_tacos_y1_start+(a_act_tacos_y1_end-a_act_tacos_y1_start)*(3-1)/11),a_ppc_launch_monthly_min_jpy/a_cur_div) -> -30000 | F29: =-F12*MAX(0,a_act_tacos_y1_start+(a_act_tacos_y1_end-a_act_tacos_y1_start)*(4-1)/11) -> -25984.848 | G29: =-G12*MAX(0,a_act_tacos_y1_start+(a_act_tacos_y1_end-a_act_tacos_y1_start)*(5-1)/11) -> -31155.303 | H29: =-H12*MAX(0,a_act_tacos_y1_start+(a_act_tacos_y1_end-a_act_tacos_y1_start)*(6-1)/11) -> -35795.455 | I29: =-I12*MAX(0,a_act_tacos_y1_start+(a_act_tacos_y1_end-a_act_tacos_y1_start)*(7-1)/11) -> -39905.303 | J29: =-J12*MAX(0,a_act_tacos_y1_start+(a_act_tacos_y1_end-a_act_tacos_y1_start)*(8-1)/11) -> -43484.848 | K29: =-K12*MAX(0,a_act_tacos_y1_start+(a_act_tacos_y1_end-a_act_tacos_y1_start)*(9-1)/11) -> -46534.091 | L29: =-L12*MAX(0,a_act_tacos_y1_start+(a_act_tacos_y1_end-a_act_tacos_y1_start)*(10-1)/11) -> -44147.727 | M29: =-M12*MAX(0,a_act_tacos_y1_start+(a_act_tacos_y1_end-a_act_tacos_y1_start)*(11-1)/11) -> -41761.364 | N29: =-N12*MAX(0,a_act_tacos_y1_start+(a_act_tacos_y1_end-a_act_tacos_y1_start)*(12-1)/11) -> -39375 | O29: =-O12*a_act_tacos_y2 -> -38115 | P29: =-P12*a_act_tacos_y2 -> -38115 | Q29: =-Q12*a_act_tacos_y2 -> -38115 | R29: =-R12*a_act_tacos_y2 -> -38115 | S29: =-S12*a_act_tacos_y2 -> -38115 | T29: =-T12*a_act_tacos_y2 -> -38115 | U29: =-U12*a_act_tacos_y2 -> -38115 | V29: =-V12*a_act_tacos_y2 -> -38115 | ... Z29: =-Z12*a_act_tacos_y2 -> -38115 | AA29: =-AA12*a_act_tacos_y3 -> -38432.625 | AB29: =-AB12*a_act_tacos_y3 -> -38432.625 | AC29: =-AC12*a_act_tacos_y3 -> -38432.625 | AD29: =-AD12*a_act_tacos_y3 -> -38432.625 | AE29: =-AE12*a_act_tacos_y3 -> -38432.625 | AF29: =-AF12*a_act_tacos_y3 -> -38432.625 | AG29: =-AG12*a_act_tacos_y3 -> -38432.625 | AH29: =-AH12*a_act_tacos_y3 -> -38432.625 | ... AL29: =-AL12*a_act_tacos_y3 -> -38432.625
B30: Content & creative | C30: =-a_content_monthly_jpy/a_cur_div -> -20000 | D30: =-a_content_monthly_jpy/a_cur_div -> -20000 | E30: =-a_content_monthly_jpy/a_cur_div -> -20000 | F30: =-a_content_monthly_jpy/a_cur_div -> -20000 | G30: =-a_content_monthly_jpy/a_cur_div -> -20000 | H30: =-a_content_monthly_jpy/a_cur_div -> -20000 | I30: =-a_content_monthly_jpy/a_cur_div -> -20000 | J30: =-a_content_monthly_jpy/a_cur_div -> -20000 | ... AL30: =-a_content_monthly_jpy/a_cur_div -> -20000
B31: Influencers & affiliates | C31: =-a_influencer_monthly_jpy/a_cur_div -> 0 | D31: =-a_influencer_monthly_jpy/a_cur_div -> 0 | E31: =-a_influencer_monthly_jpy/a_cur_div -> 0 | F31: =-a_influencer_monthly_jpy/a_cur_div -> 0 | G31: =-a_influencer_monthly_jpy/a_cur_div -> 0 | H31: =-a_influencer_monthly_jpy/a_cur_div -> 0 | I31: =-a_influencer_monthly_jpy/a_cur_div -> 0 | J31: =-a_influencer_monthly_jpy/a_cur_div -> 0 | ... AL31: =-a_influencer_monthly_jpy/a_cur_div -> 0
B32: Subscription | C32: =-a_subscription_monthly_jpy/a_products_sharing_overhead/a_cur_div -> -4900 | D32: =-a_subscription_monthly_jpy/a_products_sharing_overhead/a_cur_div -> -4900 | E32: =-a_subscription_monthly_jpy/a_products_sharing_overhead/a_cur_div -> -4900 | F32: =-a_subscription_monthly_jpy/a_products_sharing_overhead/a_cur_div -> -4900 | G32: =-a_subscription_monthly_jpy/a_products_sharing_overhead/a_cur_div -> -4900 | H32: =-a_subscription_monthly_jpy/a_products_sharing_overhead/a_cur_div -> -4900 | I32: =-a_subscription_monthly_jpy/a_products_sharing_overhead/a_cur_div -> -4900 | J32: =-a_subscription_monthly_jpy/a_products_sharing_overhead/a_cur_div -> -4900 | ... AL32: =-a_subscription_monthly_jpy/a_products_sharing_overhead/a_cur_div -> -4900
B33: Insurance (PL) | C33: =-a_insurance_monthly_jpy/a_cur_div -> -3000 | D33: =-a_insurance_monthly_jpy/a_cur_div -> -3000 | E33: =-a_insurance_monthly_jpy/a_cur_div -> -3000 | F33: =-a_insurance_monthly_jpy/a_cur_div -> -3000 | G33: =-a_insurance_monthly_jpy/a_cur_div -> -3000 | H33: =-a_insurance_monthly_jpy/a_cur_div -> -3000 | I33: =-a_insurance_monthly_jpy/a_cur_div -> -3000 | J33: =-a_insurance_monthly_jpy/a_cur_div -> -3000 | ... AL33: =-a_insurance_monthly_jpy/a_cur_div -> -3000
B34: Management fee & admin | C34: =-IF(1<a_mgmt_fee_start_month,0,a_mgmt_fee_fixed_jpy*(1+a_mgmt_fee_escalation_pct)^0/a_cur_div)/a_products_sharing_overhead -> -70000 | D34: =-IF(2<a_mgmt_fee_start_month,0,a_mgmt_fee_fixed_jpy*(1+a_mgmt_fee_escalation_pct)^0/a_cur_div)/a_products_sharing_overhead -> -70000 | E34: =-IF(3<a_mgmt_fee_start_month,0,a_mgmt_fee_fixed_jpy*(1+a_mgmt_fee_escalation_pct)^0/a_cur_div)/a_products_sharing_overhead -> -70000 | F34: =-IF(4<a_mgmt_fee_start_month,0,a_mgmt_fee_fixed_jpy*(1+a_mgmt_fee_escalation_pct)^0/a_cur_div)/a_products_sharing_overhead -> -70000 | G34: =-IF(5<a_mgmt_fee_start_month,0,a_mgmt_fee_fixed_jpy*(1+a_mgmt_fee_escalation_pct)^0/a_cur_div)/a_products_sharing_overhead -> -70000 | H34: =-IF(6<a_mgmt_fee_start_month,0,a_mgmt_fee_fixed_jpy*(1+a_mgmt_fee_escalation_pct)^0/a_cur_div)/a_products_sharing_overhead -> -70000 | I34: =-IF(7<a_mgmt_fee_start_month,0,a_mgmt_fee_fixed_jpy*(1+a_mgmt_fee_escalation_pct)^0/a_cur_div)/a_products_sharing_overhead -> -70000 | J34: =-IF(8<a_mgmt_fee_start_month,0,a_mgmt_fee_fixed_jpy*(1+a_mgmt_fee_escalation_pct)^0/a_cur_div)/a_products_sharing_overhead -> -70000 | K34: =-IF(9<a_mgmt_fee_start_month,0,a_mgmt_fee_fixed_jpy*(1+a_mgmt_fee_escalation_pct)^0/a_cur_div)/a_products_sharing_overhead -> -70000 | L34: =-IF(10<a_mgmt_fee_start_month,0,a_mgmt_fee_fixed_jpy*(1+a_mgmt_fee_escalation_pct)^0/a_cur_div)/a_products_sharing_overhead -> -70000 | M34: =-IF(11<a_mgmt_fee_start_month,0,a_mgmt_fee_fixed_jpy*(1+a_mgmt_fee_escalation_pct)^0/a_cur_div)/a_products_sharing_overhead -> -70000 | N34: =-IF(12<a_mgmt_fee_start_month,0,a_mgmt_fee_fixed_jpy*(1+a_mgmt_fee_escalation_pct)^0/a_cur_div)/a_products_sharing_overhead -> -70000 | O34: =-IF(13<a_mgmt_fee_start_month,0,a_mgmt_fee_fixed_jpy*(1+a_mgmt_fee_escalation_pct)^1/a_cur_div)/a_products_sharing_overhead -> -70000 | P34: =-IF(14<a_mgmt_fee_start_month,0,a_mgmt_fee_fixed_jpy*(1+a_mgmt_fee_escalation_pct)^1/a_cur_div)/a_products_sharing_overhead -> -70000 | Q34: =-IF(15<a_mgmt_fee_start_month,0,a_mgmt_fee_fixed_jpy*(1+a_mgmt_fee_escalation_pct)^1/a_cur_div)/a_products_sharing_overhead -> -70000 | R34: =-IF(16<a_mgmt_fee_start_month,0,a_mgmt_fee_fixed_jpy*(1+a_mgmt_fee_escalation_pct)^1/a_cur_div)/a_products_sharing_overhead -> -70000 | S34: =-IF(17<a_mgmt_fee_start_month,0,a_mgmt_fee_fixed_jpy*(1+a_mgmt_fee_escalation_pct)^1/a_cur_div)/a_products_sharing_overhead -> -70000 | T34: =-IF(18<a_mgmt_fee_start_month,0,a_mgmt_fee_fixed_jpy*(1+a_mgmt_fee_escalation_pct)^1/a_cur_div)/a_products_sharing_overhead -> -70000 | U34: =-IF(19<a_mgmt_fee_start_month,0,a_mgmt_fee_fixed_jpy*(1+a_mgmt_fee_escalation_pct)^1/a_cur_div)/a_products_sharing_overhead -> -70000 | V34: =-IF(20<a_mgmt_fee_start_month,0,a_mgmt_fee_fixed_jpy*(1+a_mgmt_fee_escalation_pct)^1/a_cur_div)/a_products_sharing_overhead -> -70000 | W34: =-IF(21<a_mgmt_fee_start_month,0,a_mgmt_fee_fixed_jpy*(1+a_mgmt_fee_escalation_pct)^1/a_cur_div)/a_products_sharing_overhead -> -70000 | X34: =-IF(22<a_mgmt_fee_start_month,0,a_mgmt_fee_fixed_jpy*(1+a_mgmt_fee_escalation_pct)^1/a_cur_div)/a_products_sharing_overhead -> -70000 | Y34: =-IF(23<a_mgmt_fee_start_month,0,a_mgmt_fee_fixed_jpy*(1+a_mgmt_fee_escalation_pct)^1/a_cur_div)/a_products_sharing_overhead -> -70000 | Z34: =-IF(24<a_mgmt_fee_start_month,0,a_mgmt_fee_fixed_jpy*(1+a_mgmt_fee_escalation_pct)^1/a_cur_div)/a_products_sharing_overhead -> -70000 | AA34: =-IF(25<a_mgmt_fee_start_month,0,a_mgmt_fee_fixed_jpy*(1+a_mgmt_fee_escalation_pct)^2/a_cur_div)/a_products_sharing_overhead -> -70000 | AB34: =-IF(26<a_mgmt_fee_start_month,0,a_mgmt_fee_fixed_jpy*(1+a_mgmt_fee_escalation_pct)^2/a_cur_div)/a_products_sharing_overhead -> -70000 | AC34: =-IF(27<a_mgmt_fee_start_month,0,a_mgmt_fee_fixed_jpy*(1+a_mgmt_fee_escalation_pct)^2/a_cur_div)/a_products_sharing_overhead -> -70000 | AD34: =-IF(28<a_mgmt_fee_start_month,0,a_mgmt_fee_fixed_jpy*(1+a_mgmt_fee_escalation_pct)^2/a_cur_div)/a_products_sharing_overhead -> -70000 | AE34: =-IF(29<a_mgmt_fee_start_month,0,a_mgmt_fee_fixed_jpy*(1+a_mgmt_fee_escalation_pct)^2/a_cur_div)/a_products_sharing_overhead -> -70000 | AF34: =-IF(30<a_mgmt_fee_start_month,0,a_mgmt_fee_fixed_jpy*(1+a_mgmt_fee_escalation_pct)^2/a_cur_div)/a_products_sharing_overhead -> -70000 | AG34: =-IF(31<a_mgmt_fee_start_month,0,a_mgmt_fee_fixed_jpy*(1+a_mgmt_fee_escalation_pct)^2/a_cur_div)/a_products_sharing_overhead -> -70000 | AH34: =-IF(32<a_mgmt_fee_start_month,0,a_mgmt_fee_fixed_jpy*(1+a_mgmt_fee_escalation_pct)^2/a_cur_div)/a_products_sharing_overhead -> -70000 | AI34: =-IF(33<a_mgmt_fee_start_month,0,a_mgmt_fee_fixed_jpy*(1+a_mgmt_fee_escalation_pct)^2/a_cur_div)/a_products_sharing_overhead -> -70000 | AJ34: =-IF(34<a_mgmt_fee_start_month,0,a_mgmt_fee_fixed_jpy*(1+a_mgmt_fee_escalation_pct)^2/a_cur_div)/a_products_sharing_overhead -> -70000 | AK34: =-IF(35<a_mgmt_fee_start_month,0,a_mgmt_fee_fixed_jpy*(1+a_mgmt_fee_escalation_pct)^2/a_cur_div)/a_products_sharing_overhead -> -70000 | AL34: =-IF(36<a_mgmt_fee_start_month,0,a_mgmt_fee_fixed_jpy*(1+a_mgmt_fee_escalation_pct)^2/a_cur_div)/a_products_sharing_overhead -> -70000
B35: EBITDA | C35: =C28+C29+C30+C31+C32+C33+C34 -> -124663.71 | D35: =D28+D29+D30+D31+D32+D33+D34 -> -121120.92 | E35: =E28+E29+E30+E31+E32+E33+E34 -> -117669.36 | F35: =F28+F29+F30+F31+F32+F33+F34 -> -103227.49 | G35: =G28+G29+G30+G31+G32+G33+G34 -> -103221.23 | H35: =H28+H29+H30+H31+H32+H33+H34 -> -102468.12 | I35: =I28+I29+I30+I31+I32+I33+I34 -> -101368.77 | J35: =J28+J29+J30+J31+J32+J33+J34 -> -99739.117 | ... AL35: =AL28+AL29+AL30+AL31+AL32+AL33+AL34 -> -67324.364
B36: EBITDA margin % | C36: =IF(C17=0,0,C35/C17) -> -5.3488087 | D36: =IF(D17=0,0,D35/D17) -> -2.598401 | E36: =IF(E17=0,0,E35/E17) -> -1.6829033 | F36: =IF(F17=0,0,F35/F17) -> -1.0299342 | G36: =IF(G17=0,0,G35/G17) -> -0.82389734 | H36: =IF(H17=0,0,H35/H17) -> -0.68157179 | I36: =IF(I17=0,0,I35/I17) -> -0.57793663 | J36: =IF(J17=0,0,J35/J17) -> -0.49756476 | ... AL36: =IF(AL17=0,0,AL35/AL17) -> -0.20390745
B37: Operating metrics
B38: Advertising ROAS | C38: =IF(C29=0,0,-C12/C29) -> 0.97222222 | D38: =IF(D29=0,0,-D12/D29) -> 1.9444444 | E38: =IF(E29=0,0,-E12/E29) -> 2.9166667 | F38: =IF(F29=0,0,-F12/F29) -> 4.4897959 | G38: =IF(G29=0,0,-G12/G29) -> 4.6808511 | H38: =IF(H29=0,0,-H12/H29) -> 4.8888889 | I38: =IF(I29=0,0,-I12/I29) -> 5.1162791 | J38: =IF(J29=0,0,-J12/J29) -> 5.3658537 | ... AL38: =IF(AL29=0,0,-AL12/AL29) -> 10
B39: Inventory turnover | C39: =IF(('Investment and Cash'!E8+'Investment and Cash'!E11)=0,0,24*C10/('Investment and Cash'!E8+'Investment and Cash'!E11)) -> 1.2631579 | D39: =IF(('Investment and Cash'!F8+'Investment and Cash'!F11)=0,0,24*D10/('Investment and Cash'!F8+'Investment and Cash'!F11)) -> 3 | E39: =IF(('Investment and Cash'!G8+'Investment and Cash'!G11)=0,0,24*E10/('Investment and Cash'!G8+'Investment and Cash'!G11)) -> 6.5454545 | F39: =IF(('Investment and Cash'!H8+'Investment and Cash'!H11)=0,0,24*F10/('Investment and Cash'!H8+'Investment and Cash'!H11)) -> 6.8571429 | G39: =IF(('Investment and Cash'!I8+'Investment and Cash'!I11)=0,0,24*G10/('Investment and Cash'!I8+'Investment and Cash'!I11)) -> 7.0588235 | H39: =IF(('Investment and Cash'!J8+'Investment and Cash'!J11)=0,0,24*H10/('Investment and Cash'!J8+'Investment and Cash'!J11)) -> 7.2 | I39: =IF(('Investment and Cash'!K8+'Investment and Cash'!K11)=0,0,24*I10/('Investment and Cash'!K8+'Investment and Cash'!K11)) -> 7.3043478 | J39: =IF(('Investment and Cash'!L8+'Investment and Cash'!L11)=0,0,24*J10/('Investment and Cash'!L8+'Investment and Cash'!L11)) -> 7.3846154 | ... AL39: =IF(('Investment and Cash'!AN8+'Investment and Cash'!AN11)=0,0,24*AL10/('Investment and Cash'!AN8+'Investment and Cash'!AN11)) -> 24
B40: Return rate | C40: =IF(C12=0,0,-C16/C12) -> 0.02 | D40: =IF(D12=0,0,-D16/D12) -> 0.02 | E40: =IF(E12=0,0,-E16/E12) -> 0.02 | F40: =IF(F12=0,0,-F16/F12) -> 0.02 | G40: =IF(G12=0,0,-G16/G12) -> 0.02 | H40: =IF(H12=0,0,-H16/H12) -> 0.02 | I40: =IF(I12=0,0,-I16/I12) -> 0.02 | J40: =IF(J12=0,0,-J16/J12) -> 0.02 | ... AL40: =IF(AL12=0,0,-AL16/AL12) -> 0.02
B41: · long-term storage (pessimistic) | C41: 0 | D41: 0 | E41: 0 | F41: 0 | G41: 0 | H41: 0 | I41: 0 | J41: 0 | K41: 0 | L41: 0 | M41: 0 | N41: 0 | O41: 0 | P41: 0 | Q41: 0 | R41: 0 | S41: 0 | T41: 0 | U41: 0 | V41: 0 | W41: 0 | X41: 0 | Y41: 0 | Z41: 0 | AA41: 0 | AB41: 0 | AC41: 0 | AD41: 0 | AE41: 0 | AF41: 0 | AG41: 0 | AH41: 0 | AI41: 0 | AJ41: 0 | AK41: 0 | AL41: 0
B42: · long-term storage (base) | C42: 0 | D42: 0 | E42: 0 | F42: 0 | G42: 0 | H42: 0 | I42: 0 | J42: 0 | K42: 0 | L42: 0 | M42: 0 | N42: 0 | O42: 0 | P42: 0 | Q42: 0 | R42: 0 | S42: 0 | T42: 0 | U42: 0 | V42: 0 | W42: 0 | X42: 0 | Y42: 0 | Z42: 0 | AA42: 0 | AB42: 0 | AC42: 0 | AD42: 0 | AE42: 0 | AF42: 0 | AG42: 0 | AH42: 0 | AI42: 0 | AJ42: 0 | AK42: 0 | AL42: 0
B43: · long-term storage (optimistic) | C43: 0 | D43: 0 | E43: 0 | F43: 0 | G43: 0 | H43: 0 | I43: 0 | J43: 0 | K43: 0 | L43: 0 | M43: 0 | N43: 0 | O43: 0 | P43: 0 | Q43: 0 | R43: 0 | S43: 0 | T43: 0 | U43: 0 | V43: 0 | W43: 0 | X43: 0 | Y43: 0 | Z43: 0 | AA43: 0 | AB43: 0 | AC43: 0 | AD43: 0 | AE43: 0 | AF43: 0 | AG43: 0 | AH43: 0 | AI43: 0 | AJ43: 0 | AK43: 0 | AL43: 0

Sheet PL Annual
B2: Made for Doraemon | F2: ="Currency: "&a_currency&" · switch on the Dashboard" -> Currency: JPY · switch on the Dashboard
B4: P&L — annual
B5: Yearly rollups of the live monthly P&L.
B7: P&L line | C7: Year 1 | D7: Year 2 | E7: Year 3 | F7: Total
B8: Units sold | C8: =SUM('PL Monthly'!C10:N10) -> 600 | D8: =SUM('PL Monthly'!O10:Z10) -> 1089 | E8: =SUM('PL Monthly'!AA10:AL10) -> 1317.69 | F8: =SUM('PL Monthly'!C10:AL10) -> 3006.69
B9: Gross sales | C9: =SUM('PL Monthly'!C12:N12) -> 2100000 | D9: =SUM('PL Monthly'!O12:Z12) -> 3811500 | E9: =SUM('PL Monthly'!AA12:AL12) -> 4611915 | F9: =SUM('PL Monthly'!C12:AL12) -> 10523415
B10: Output JCT | C10: =SUM('PL Monthly'!C13:N13) -> -190909.09 | D10: =SUM('PL Monthly'!O13:Z13) -> -346500 | E10: =SUM('PL Monthly'!AA13:AL13) -> -419265 | F10: =SUM('PL Monthly'!C13:AL13) -> -956674.09
B11: Amazon Points | C11: =SUM('PL Monthly'!C14:N14) -> -21000 | D11: =SUM('PL Monthly'!O14:Z14) -> -38115 | E11: =SUM('PL Monthly'!AA14:AL14) -> -46119.15 | F11: =SUM('PL Monthly'!C14:AL14) -> -105234.15
B12: Promotions & deals | C12: =SUM('PL Monthly'!C15:N15) -> -52500 | D12: =SUM('PL Monthly'!O15:Z15) -> -76230 | E12: =SUM('PL Monthly'!AA15:AL15) -> -92238.3 | F12: =SUM('PL Monthly'!C15:AL15) -> -220968.3
B13: Returns | C13: =SUM('PL Monthly'!C16:N16) -> -42000 | D13: =SUM('PL Monthly'!O16:Z16) -> -76230 | E13: =SUM('PL Monthly'!AA16:AL16) -> -92238.3 | F13: =SUM('PL Monthly'!C16:AL16) -> -210468.3
B14: Net revenue | C14: =SUM('PL Monthly'!C17:N17) -> 1793590.9 | D14: =SUM('PL Monthly'!O17:Z17) -> 3274425 | E14: =SUM('PL Monthly'!AA17:AL17) -> 3962054.2 | F14: =SUM('PL Monthly'!C17:AL17) -> 9030070.2
B15: Unit procurement cost | C15: =SUM('PL Monthly'!C18:N18) -> -945000 | D15: =SUM('PL Monthly'!O18:Z18) -> -1715175 | E15: =SUM('PL Monthly'!AA18:AL18) -> -2075361.8 | F15: =SUM('PL Monthly'!C18:AL18) -> -4735536.8
B16: Domestic logistics to FBA | C16: =SUM('PL Monthly'!C19:N19) -> -30000 | D16: =SUM('PL Monthly'!O19:Z19) -> -54450 | E16: =SUM('PL Monthly'!AA19:AL19) -> -65884.5 | F16: =SUM('PL Monthly'!C19:AL19) -> -150334.5
B17: Inspection / QC | C17: =SUM('PL Monthly'!C20:N20) -> 0 | D17: =SUM('PL Monthly'!O20:Z20) -> 0 | E17: =SUM('PL Monthly'!AA20:AL20) -> 0 | F17: =SUM('PL Monthly'!C20:AL20) -> 0
B18: Shrinkage & write-offs | C18: =SUM('PL Monthly'!C21:N21) -> -9750 | D18: =SUM('PL Monthly'!O21:Z21) -> -17696.25 | E18: =SUM('PL Monthly'!AA21:AL21) -> -21412.463 | F18: =SUM('PL Monthly'!C21:AL21) -> -48858.713
B19: Gross profit | C19: =SUM('PL Monthly'!C22:N22) -> 808840.91 | D19: =SUM('PL Monthly'!O22:Z22) -> 1487103.8 | E19: =SUM('PL Monthly'!AA22:AL22) -> 1799395.5 | F19: =SUM('PL Monthly'!C22:AL22) -> 4095340.2
B20: Referral fee | C20: =SUM('PL Monthly'!C23:N23) -> -218400 | D20: =SUM('PL Monthly'!O23:Z23) -> -396396 | E20: =SUM('PL Monthly'!AA23:AL23) -> -479639.16 | F20: =SUM('PL Monthly'!C23:AL23) -> -1094435.2
... B32: EBITDA | C32: =SUM('PL Monthly'!C35:N35) -> -1249418.4 | D32: =SUM('PL Monthly'!O35:Z35) -> -952566.69 | E32: =SUM('PL Monthly'!AA35:AL35) -> -813215.13 | F32: =SUM('PL Monthly'!C35:AL35) -> -3015200.2
B33: Operating metrics
B34: Advertising ROAS | C34: =IF(SUM('PL Monthly'!C29:N29)=0,0,-SUM('PL Monthly'!C12:N12)/SUM('PL Monthly'!C29:N29)) -> 4.7929454 | D34: =IF(SUM('PL Monthly'!O29:Z29)=0,0,-SUM('PL Monthly'!O12:Z12)/SUM('PL Monthly'!O29:Z29)) -> 8.3333333 | E34: =IF(SUM('PL Monthly'!AA29:AL29)=0,0,-SUM('PL Monthly'!AA12:AL12)/SUM('PL Monthly'!AA29:AL29)) -> 10 | F34: =IF(SUM('PL Monthly'!C29:AL29)=0,0,-SUM('PL Monthly'!C12:AL12)/SUM('PL Monthly'!C29:AL29)) -> 7.7565381
B35: Inventory turnover | C35: =IF((SUM('Investment and Cash'!E8:P8)+SUM('Investment and Cash'!E11:P11))=0,0,24*SUM('PL Monthly'!C10:N10)/(SUM('Investment and Cash'!E8:P8)+SUM('Investment and Cash'!E11:P11))) -> 6.7033905 | D35: =IF((SUM('Investment and Cash'!Q8:AB8)+SUM('Investment and Cash'!Q11:AB11))=0,0,24*SUM('PL Monthly'!O10:Z10)/(SUM('Investment and Cash'!Q8:AB8)+SUM('Investment and Cash'!Q11:AB11))) -> 7.907743 | E35: =IF((SUM('Investment and Cash'!AC8:AN8)+SUM('Investment and Cash'!AC11:AN11))=0,0,24*SUM('PL Monthly'!AA10:AL10)/(SUM('Investment and Cash'!AC8:AN8)+SUM('Investment and Cash'!AC11:AN11))) -> 8.4705882 | F35: =IF((SUM('Investment and Cash'!E8:AN8)+SUM('Investment and Cash'!E11:AN11))=0,0,24*SUM('PL Monthly'!C10:AL10)/(SUM('Investment and Cash'!E8:AN8)+SUM('Investment and Cash'!E11:AN11))) -> 7.8548632
B36: Return rate | C36: =IF(SUM('PL Monthly'!C12:N12)=0,0,-SUM('PL Monthly'!C16:N16)/SUM('PL Monthly'!C12:N12)) -> 0.02 | D36: =IF(SUM('PL Monthly'!O12:Z12)=0,0,-SUM('PL Monthly'!O16:Z16)/SUM('PL Monthly'!O12:Z12)) -> 0.02 | E36: =IF(SUM('PL Monthly'!AA12:AL12)=0,0,-SUM('PL Monthly'!AA16:AL16)/SUM('PL Monthly'!AA12:AL12)) -> 0.02 | F36: =IF(SUM('PL Monthly'!C12:AL12)=0,0,-SUM('PL Monthly'!C16:AL16)/SUM('PL Monthly'!C12:AL12)) -> 0.02

Sheet Investment and Cash
B2: Made for Doraemon | N2: ="Currency: "&a_currency&" · switch on the Dashboard" -> Currency: JPY · switch on the Dashboard
B4: Investment & Cash
B5: Pre-launch months + 36 sales months. Peak funding need already includes launch costs and the first inventory order.
B7: Cash line | C7: PRE-2 · Jun | D7: PRE-1 · Jul | E7: M1 · Aug | F7: M2 · Sep | G7: M3 · Oct | H7: M4 · Nov | I7: M5 · Dec | J7: M6 · Jan | K7: M7 · Feb | L7: M8 · Mar | M7: M9 · Apr | N7: M10 · May | O7: M11 · Jun | P7: M12 · Jul | Q7: M13 · Aug | R7: M14 · Sep | S7: M15 · Oct | T7: M16 · Nov | U7: M17 · Dec | V7: M18 · Jan | W7: M19 · Feb | X7: M20 · Mar | Y7: M21 · Apr | Z7: M22 · May | AA7: M23 · Jun | AB7: M24 · Jul | AC7: M25 · Aug | AD7: M26 · Sep | AE7: M27 · Oct | AF7: M28 · Nov | AG7: M29 · Dec | AH7: M30 · Jan | AI7: M31 · Feb | AJ7: M32 · Mar | AK7: M33 · Apr | AL7: M34 · May | AM7: M35 · Jun | AN7: M36 · Jul
B8: Stock opening | C8: =0+C10 -> 0 | D8: =C11+D10 -> 0 | E8: =D11+E10 -> 83.333333 | F8: =E11+F10 -> 75 | G8: =F11+G10 -> 58.333333 | H8: =G11+H10 -> 75 | I8: =H11+I10 -> 91.666667 | J8: =I11+J10 -> 108.33333 | K8: =J11+K10 -> 125 | ... AN8: =AM11+AN10 -> 109.8075
B9: Order placed | C9: =MAX(SUM('PL Monthly'!C10:F10),a_moq_units) -> 83.333333 | D9: =IF((C11+C9-SUM('PL Monthly'!C10))<SUM('PL Monthly'!D10:E10),MAX(SUM('PL Monthly'!D10:E10)-(C11+C9-SUM('PL Monthly'!C10)),a_moq_units),0) -> 0 | E9: =IF((D11+C9+D9-SUM('PL Monthly'!C10:D10))<SUM('PL Monthly'!E10:F10),MAX(SUM('PL Monthly'!E10:F10)-(D11+C9+D9-SUM('PL Monthly'!C10:D10)),a_moq_units),0) -> 0 | F9: =IF((E11+D9+E9-SUM('PL Monthly'!D10:E10))<SUM('PL Monthly'!F10:G10),MAX(SUM('PL Monthly'!F10:G10)-(E11+D9+E9-SUM('PL Monthly'!D10:E10)),a_moq_units),0) -> 41.666667 | G9: =IF((F11+E9+F9-SUM('PL Monthly'!E10:F10))<SUM('PL Monthly'!G10:H10),MAX(SUM('PL Monthly'!G10:H10)-(F11+E9+F9-SUM('PL Monthly'!E10:F10)),a_moq_units),0) -> 50 | H9: =IF((G11+F9+G9-SUM('PL Monthly'!F10:G10))<SUM('PL Monthly'!H10:I10),MAX(SUM('PL Monthly'!H10:I10)-(G11+F9+G9-SUM('PL Monthly'!F10:G10)),a_moq_units),0) -> 58.333333 | I9: =IF((H11+G9+H9-SUM('PL Monthly'!G10:H10))<SUM('PL Monthly'!I10:J10),MAX(SUM('PL Monthly'!I10:J10)-(H11+G9+H9-SUM('PL Monthly'!G10:H10)),a_moq_units),0) -> 66.666667 | J9: =IF((I11+H9+I9-SUM('PL Monthly'!H10:I10))<SUM('PL Monthly'!J10:K10),MAX(SUM('PL Monthly'!J10:K10)-(I11+H9+I9-SUM('PL Monthly'!H10:I10)),a_moq_units),0) -> 75 | K9: =IF((J11+I9+J9-SUM('PL Monthly'!I10:J10))<SUM('PL Monthly'!K10:L10),MAX(SUM('PL Monthly'!K10:L10)-(J11+I9+J9-SUM('PL Monthly'!I10:J10)),a_moq_units),0) -> 75 | L9: =IF((K11+J9+K9-SUM('PL Monthly'!J10:K10))<SUM('PL Monthly'!L10:M10),MAX(SUM('PL Monthly'!L10:M10)-(K11+J9+K9-SUM('PL Monthly'!J10:K10)),a_moq_units),0) -> 75 | ... AK9: =IF((AJ11+AI9+AJ9-SUM('PL Monthly'!AI10:AJ10))<SUM('PL Monthly'!AK10:AL10),MAX(SUM('PL Monthly'!AK10:AL10)-(AJ11+AI9+AJ9-SUM('PL Monthly'!AI10:AJ10)),a_moq_units),0) -> 109.8075 | AL9: =IF((AK11+AJ9+AK9-SUM('PL Monthly'!AJ10:AK10))<SUM('PL Monthly'!AL10),MAX(SUM('PL Monthly'!AL10)-(AK11+AJ9+AK9-SUM('PL Monthly'!AJ10:AK10)),a_moq_units),0) -> 0 | AM9: =0 -> 0 | AN9: =0 -> 0
B10: Receipts | C10: =0 -> 0 | D10: =0 -> 0 | E10: =C9 -> 83.333333 | F10: =D9 -> 0 | G10: =E9 -> 0 | H10: =F9 -> 41.666667 | I10: =G9 -> 50 | J10: =H9 -> 58.333333 | K10: =I9 -> 66.666667 | L10: =J9 -> 75 | ... AN10: =AL9 -> 0
B11: Stock closing | C11: =C8-0 -> 0 | D11: =D8-0 -> 0 | E11: =E8-'PL Monthly'!C10 -> 75 | F11: =F8-'PL Monthly'!D10 -> 58.333333 | G11: =G8-'PL Monthly'!E10 -> 33.333333 | H11: =H8-'PL Monthly'!F10 -> 41.666667 | I11: =I8-'PL Monthly'!G10 -> 50 | J11: =J8-'PL Monthly'!H10 -> 58.333333 | K11: =K8-'PL Monthly'!I10 -> 66.666667 | L11: =L8-'PL Monthly'!J10 -> 75 | ... AN11: =AN8-'PL Monthly'!AL10 -> 0
B12: · net receipts | C12: =0 -> 0 | D12: =0 -> 0 | E12: ='PL Monthly'!C12*(1-a_return_rate)+'PL Monthly'!C14+'PL Monthly'!C15+(1+a_jct_rate_standard)*('PL Monthly'!C23+'PL Monthly'!C24+'PL Monthly'!C25+'PL Monthly'!C26+'PL Monthly'!C27) -> 18925.541 | F12: ='PL Monthly'!D12*(1-a_return_rate)+'PL Monthly'!D14+'PL Monthly'!D15+(1+a_jct_rate_standard)*('PL Monthly'!D23+'PL Monthly'!D24+'PL Monthly'!D25+'PL Monthly'!D26+'PL Monthly'!D27) -> 38188.237 | G12: ='PL Monthly'!E12*(1-a_return_rate)+'PL Monthly'!E14+'PL Monthly'!E15+(1+a_jct_rate_standard)*('PL Monthly'!E23+'PL Monthly'!E24+'PL Monthly'!E25+'PL Monthly'!E26+'PL Monthly'!E27) -> 57350.576 | H12: ='PL Monthly'!F12*(1-a_return_rate)+'PL Monthly'!F14+'PL Monthly'!F15+(1+a_jct_rate_standard)*('PL Monthly'!F23+'PL Monthly'!F24+'PL Monthly'!F25+'PL Monthly'!F26+'PL Monthly'!F27) -> 83485.591 | I12: ='PL Monthly'!G12*(1-a_return_rate)+'PL Monthly'!G14+'PL Monthly'!G15+(1+a_jct_rate_standard)*('PL Monthly'!G23+'PL Monthly'!G24+'PL Monthly'!G25+'PL Monthly'!G26+'PL Monthly'!G27) -> 104370.61 | J12: ='PL Monthly'!H12*(1-a_return_rate)+'PL Monthly'!H14+'PL Monthly'!H15+(1+a_jct_rate_standard)*('PL Monthly'!H23+'PL Monthly'!H24+'PL Monthly'!H25+'PL Monthly'!H26+'PL Monthly'!H27) -> 125493.82 | K12: ='PL Monthly'!I12*(1-a_return_rate)+'PL Monthly'!I14+'PL Monthly'!I15+(1+a_jct_rate_standard)*('PL Monthly'!I23+'PL Monthly'!I24+'PL Monthly'!I25+'PL Monthly'!I26+'PL Monthly'!I27) -> 146414.56 | L12: ='PL Monthly'!J12*(1-a_return_rate)+'PL Monthly'!J14+'PL Monthly'!J15+(1+a_jct_rate_standard)*('PL Monthly'!J23+'PL Monthly'!J24+'PL Monthly'!J25+'PL Monthly'!J26+'PL Monthly'!J27) -> 167335.3 | ... AN12: ='PL Monthly'!AL12*(1-a_return_rate)+'PL Monthly'!AL14+'PL Monthly'!AL15+(1+a_jct_rate_standard)*('PL Monthly'!AL23+'PL Monthly'!AL24+'PL Monthly'!AL25+'PL Monthly'!AL26+'PL Monthly'!AL27) -> 276074.43
B13: · output jct | C13: =0 -> 0 | D13: =0 -> 0 | E13: =-'PL Monthly'!C13 -> 2651.5152 | F13: =-'PL Monthly'!D13 -> 5303.0303 | G13: =-'PL Monthly'!E13 -> 7954.5455 | H13: =-'PL Monthly'!F13 -> 10606.061 | I13: =-'PL Monthly'!G13 -> 13257.576 | J13: =-'PL Monthly'!H13 -> 15909.091 | K13: =-'PL Monthly'!I13 -> 18560.606 | L13: =-'PL Monthly'!J13 -> 21212.121 | ... AN13: =-'PL Monthly'!AL13 -> 34938.75
B14: · input credits | C14: =a_jct_rate_output*(a_prepay_order_pct*C9+(1-a_prepay_order_pct)*0)*a_unit_cogs_jpy/a_cur_div*a_supplier_invoice_credit_rate+a_jct_rate_standard*C10*(a_logistics_jpy_per_unit+a_inspection_jpy_per_unit)/a_cur_div+0 -> 6562.5 | D14: =a_jct_rate_output*(a_prepay_order_pct*D9+(1-a_prepay_order_pct)*0)*a_unit_cogs_jpy/a_cur_div*a_supplier_invoice_credit_rate+a_jct_rate_standard*D10*(a_logistics_jpy_per_unit+a_inspection_jpy_per_unit)/a_cur_div+0 -> 0 | E14: =a_jct_rate_output*(a_prepay_order_pct*E9+(1-a_prepay_order_pct)*C9)*a_unit_cogs_jpy/a_cur_div*a_supplier_invoice_credit_rate+a_jct_rate_standard*E10*(a_logistics_jpy_per_unit+a_inspection_jpy_per_unit)/a_cur_div+a_jct_rate_standard*(-('PL Monthly'!C23+'PL Monthly'!C24+'PL Monthly'!C25+'PL Monthly'!C26+'PL Monthly'!C27)) -> 7618.5114 | F14: =a_jct_rate_output*(a_prepay_order_pct*F9+(1-a_prepay_order_pct)*D9)*a_unit_cogs_jpy/a_cur_div*a_supplier_invoice_credit_rate+a_jct_rate_standard*F10*(a_logistics_jpy_per_unit+a_inspection_jpy_per_unit)/a_cur_div+a_jct_rate_standard*(-('PL Monthly'!D23+'PL Monthly'!D24+'PL Monthly'!D25+'PL Monthly'!D26+'PL Monthly'!D27)) -> 4529.2891 | G14: =a_jct_rate_output*(a_prepay_order_pct*G9+(1-a_prepay_order_pct)*E9)*a_unit_cogs_jpy/a_cur_div*a_supplier_invoice_credit_rate+a_jct_rate_standard*G10*(a_logistics_jpy_per_unit+a_inspection_jpy_per_unit)/a_cur_div+a_jct_rate_standard*(-('PL Monthly'!E23+'PL Monthly'!E24+'PL Monthly'!E25+'PL Monthly'!E26+'PL Monthly'!E27)) -> 5803.3567 | H14: =a_jct_rate_output*(a_prepay_order_pct*H9+(1-a_prepay_order_pct)*F9)*a_unit_cogs_jpy/a_cur_div*a_supplier_invoice_credit_rate+a_jct_rate_standard*H10*(a_logistics_jpy_per_unit+a_inspection_jpy_per_unit)/a_cur_div+a_jct_rate_standard*(-('PL Monthly'!F23+'PL Monthly'!F24+'PL Monthly'!F25+'PL Monthly'!F26+'PL Monthly'!F27)) -> 10569.492 | I14: =a_jct_rate_output*(a_prepay_order_pct*I9+(1-a_prepay_order_pct)*G9)*a_unit_cogs_jpy/a_cur_div*a_supplier_invoice_credit_rate+a_jct_rate_standard*I10*(a_logistics_jpy_per_unit+a_inspection_jpy_per_unit)/a_cur_div+a_jct_rate_standard*(-('PL Monthly'!G23+'PL Monthly'!G24+'PL Monthly'!G25+'PL Monthly'!G26+'PL Monthly'!G27)) -> 12543.96 | J14: =a_jct_rate_output*(a_prepay_order_pct*J9+(1-a_prepay_order_pct)*H9)*a_unit_cogs_jpy/a_cur_div*a_supplier_invoice_credit_rate+a_jct_rate_standard*J10*(a_logistics_jpy_per_unit+a_inspection_jpy_per_unit)/a_cur_div+a_jct_rate_standard*(-('PL Monthly'!H23+'PL Monthly'!H24+'PL Monthly'!H25+'PL Monthly'!H26+'PL Monthly'!H27)) -> 14496.774 | K14: =a_jct_rate_output*(a_prepay_order_pct*K9+(1-a_prepay_order_pct)*I9)*a_unit_cogs_jpy/a_cur_div*a_supplier_invoice_credit_rate+a_jct_rate_standard*K10*(a_logistics_jpy_per_unit+a_inspection_jpy_per_unit)/a_cur_div+a_jct_rate_standard*(-('PL Monthly'!I23+'PL Monthly'!I24+'PL Monthly'!I25+'PL Monthly'!I26+'PL Monthly'!I27)) -> 15811.745 | L14: =a_jct_rate_output*(a_prepay_order_pct*L9+(1-a_prepay_order_pct)*J9)*a_unit_cogs_jpy/a_cur_div*a_supplier_invoice_credit_rate+a_jct_rate_standard*L10*(a_logistics_jpy_per_unit+a_inspection_jpy_per_unit)/a_cur_div+a_jct_rate_standard*(-('PL Monthly'!J23+'PL Monthly'!J24+'PL Monthly'!J25+'PL Monthly'!J26+'PL Monthly'!J27)) -> 17126.715 | ... AN14: =a_jct_rate_output*(a_prepay_order_pct*AN9+(1-a_prepay_order_pct)*AL9)*a_unit_cogs_jpy/a_cur_div*a_supplier_invoice_credit_rate+a_jct_rate_standard*AN10*(a_logistics_jpy_per_unit+a_inspection_jpy_per_unit)/a_cur_div+a_jct_rate_standard*(-('PL Monthly'!AL23+'PL Monthly'!AL24+'PL Monthly'!AL25+'PL Monthly'!AL26+'PL Monthly'!AL27)) -> 8094.1367
B15: Supplier payments | C15: =-(a_prepay_order_pct*C9+(1-a_prepay_order_pct)*0)*a_unit_cogs_jpy/a_cur_div -> -65625 | D15: =-(a_prepay_order_pct*D9+(1-a_prepay_order_pct)*0)*a_unit_cogs_jpy/a_cur_div -> 0 | E15: =-(a_prepay_order_pct*E9+(1-a_prepay_order_pct)*C9)*a_unit_cogs_jpy/a_cur_div -> -65625 | F15: =-(a_prepay_order_pct*F9+(1-a_prepay_order_pct)*D9)*a_unit_cogs_jpy/a_cur_div -> -32812.5 | G15: =-(a_prepay_order_pct*G9+(1-a_prepay_order_pct)*E9)*a_unit_cogs_jpy/a_cur_div -> -39375 | H15: =-(a_prepay_order_pct*H9+(1-a_prepay_order_pct)*F9)*a_unit_cogs_jpy/a_cur_div -> -78750 | I15: =-(a_prepay_order_pct*I9+(1-a_prepay_order_pct)*G9)*a_unit_cogs_jpy/a_cur_div -> -91875 | J15: =-(a_prepay_order_pct*J9+(1-a_prepay_order_pct)*H9)*a_unit_cogs_jpy/a_cur_div -> -105000 | K15: =-(a_prepay_order_pct*K9+(1-a_prepay_order_pct)*I9)*a_unit_cogs_jpy/a_cur_div -> -111562.5 | L15: =-(a_prepay_order_pct*L9+(1-a_prepay_order_pct)*J9)*a_unit_cogs_jpy/a_cur_div -> -118125 | ... AN15: =-(a_prepay_order_pct*AN9+(1-a_prepay_order_pct)*AL9)*a_unit_cogs_jpy/a_cur_div -> 0
B16: Domestic logistics paid | C16: =-C10*(a_logistics_jpy_per_unit+a_inspection_jpy_per_unit)/a_cur_div -> 0 | D16: =-D10*(a_logistics_jpy_per_unit+a_inspection_jpy_per_unit)/a_cur_div -> 0 | E16: =-E10*(a_logistics_jpy_per_unit+a_inspection_jpy_per_unit)/a_cur_div -> -4166.6667 | F16: =-F10*(a_logistics_jpy_per_unit+a_inspection_jpy_per_unit)/a_cur_div -> 0 | G16: =-G10*(a_logistics_jpy_per_unit+a_inspection_jpy_per_unit)/a_cur_div -> 0 | H16: =-H10*(a_logistics_jpy_per_unit+a_inspection_jpy_per_unit)/a_cur_div -> -2083.3333 | I16: =-I10*(a_logistics_jpy_per_unit+a_inspection_jpy_per_unit)/a_cur_div -> -2500 | J16: =-J10*(a_logistics_jpy_per_unit+a_inspection_jpy_per_unit)/a_cur_div -> -2916.6667 | ... AN16: =-AN10*(a_logistics_jpy_per_unit+a_inspection_jpy_per_unit)/a_cur_div -> 0
B17: Input JCT on purchases | C17: =-(a_jct_rate_output*(a_prepay_order_pct*C9+(1-a_prepay_order_pct)*0)*a_unit_cogs_jpy/a_cur_div+a_jct_rate_standard*C10*(a_logistics_jpy_per_unit+a_inspection_jpy_per_unit)/a_cur_div) -> -6562.5 | D17: =-(a_jct_rate_output*(a_prepay_order_pct*D9+(1-a_prepay_order_pct)*0)*a_unit_cogs_jpy/a_cur_div+a_jct_rate_standard*D10*(a_logistics_jpy_per_unit+a_inspection_jpy_per_unit)/a_cur_div) -> 0 | E17: =-(a_jct_rate_output*(a_prepay_order_pct*E9+(1-a_prepay_order_pct)*C9)*a_unit_cogs_jpy/a_cur_div+a_jct_rate_standard*E10*(a_logistics_jpy_per_unit+a_inspection_jpy_per_unit)/a_cur_div) -> -6979.1667 | F17: =-(a_jct_rate_output*(a_prepay_order_pct*F9+(1-a_prepay_order_pct)*D9)*a_unit_cogs_jpy/a_cur_div+a_jct_rate_standard*F10*(a_logistics_jpy_per_unit+a_inspection_jpy_per_unit)/a_cur_div) -> -3281.25 | G17: =-(a_jct_rate_output*(a_prepay_order_pct*G9+(1-a_prepay_order_pct)*E9)*a_unit_cogs_jpy/a_cur_div+a_jct_rate_standard*G10*(a_logistics_jpy_per_unit+a_inspection_jpy_per_unit)/a_cur_div) -> -3937.5 | H17: =-(a_jct_rate_output*(a_prepay_order_pct*H9+(1-a_prepay_order_pct)*F9)*a_unit_cogs_jpy/a_cur_div+a_jct_rate_standard*H10*(a_logistics_jpy_per_unit+a_inspection_jpy_per_unit)/a_cur_div) -> -8083.3333 | I17: =-(a_jct_rate_output*(a_prepay_order_pct*I9+(1-a_prepay_order_pct)*G9)*a_unit_cogs_jpy/a_cur_div+a_jct_rate_standard*I10*(a_logistics_jpy_per_unit+a_inspection_jpy_per_unit)/a_cur_div) -> -9437.5 | J17: =-(a_jct_rate_output*(a_prepay_order_pct*J9+(1-a_prepay_order_pct)*H9)*a_unit_cogs_jpy/a_cur_div+a_jct_rate_standard*J10*(a_logistics_jpy_per_unit+a_inspection_jpy_per_unit)/a_cur_div) -> -10791.667 | K17: =-(a_jct_rate_output*(a_prepay_order_pct*K9+(1-a_prepay_order_pct)*I9)*a_unit_cogs_jpy/a_cur_div+a_jct_rate_standard*K10*(a_logistics_jpy_per_unit+a_inspection_jpy_per_unit)/a_cur_div) -> -11489.583 | L17: =-(a_jct_rate_output*(a_prepay_order_pct*L9+(1-a_prepay_order_pct)*J9)*a_unit_cogs_jpy/a_cur_div+a_jct_rate_standard*L10*(a_logistics_jpy_per_unit+a_inspection_jpy_per_unit)/a_cur_div) -> -12187.5 | ... AN17: =-(a_jct_rate_output*(a_prepay_order_pct*AN9+(1-a_prepay_order_pct)*AL9)*a_unit_cogs_jpy/a_cur_div+a_jct_rate_standard*AN10*(a_logistics_jpy_per_unit+a_inspection_jpy_per_unit)/a_cur_div) -> 0
B18: Launch CAPEX | C18: =-a_act_capex_total/a_cur_div -> -519200 | D18: =0 -> 0 | E18: =0 -> 0 | F18: =0 -> 0 | G18: =0 -> 0 | H18: =0 -> 0 | I18: =0 -> 0 | J18: =0 -> 0 | K18: =0 -> 0 | ... AN18: =0 -> 0
B19: Opex & marketing cash | C19: =0 -> 0 | D19: =0 -> 0 | E19: ='PL Monthly'!C29+'PL Monthly'!C30+'PL Monthly'!C31+'PL Monthly'!C32+'PL Monthly'!C33+'PL Monthly'!C34 -> -127900 | F19: ='PL Monthly'!D29+'PL Monthly'!D30+'PL Monthly'!D31+'PL Monthly'!D32+'PL Monthly'!D33+'PL Monthly'!D34 -> -127900 | G19: ='PL Monthly'!E29+'PL Monthly'!E30+'PL Monthly'!E31+'PL Monthly'!E32+'PL Monthly'!E33+'PL Monthly'!E34 -> -127900 | H19: ='PL Monthly'!F29+'PL Monthly'!F30+'PL Monthly'!F31+'PL Monthly'!F32+'PL Monthly'!F33+'PL Monthly'!F34 -> -123884.85 | I19: ='PL Monthly'!G29+'PL Monthly'!G30+'PL Monthly'!G31+'PL Monthly'!G32+'PL Monthly'!G33+'PL Monthly'!G34 -> -129055.3 | J19: ='PL Monthly'!H29+'PL Monthly'!H30+'PL Monthly'!H31+'PL Monthly'!H32+'PL Monthly'!H33+'PL Monthly'!H34 -> -133695.45 | K19: ='PL Monthly'!I29+'PL Monthly'!I30+'PL Monthly'!I31+'PL Monthly'!I32+'PL Monthly'!I33+'PL Monthly'!I34 -> -137805.3 | L19: ='PL Monthly'!J29+'PL Monthly'!J30+'PL Monthly'!J31+'PL Monthly'!J32+'PL Monthly'!J33+'PL Monthly'!J34 -> -141384.85 | ... AN19: ='PL Monthly'!AL29+'PL Monthly'!AL30+'PL Monthly'!AL31+'PL Monthly'!AL32+'PL Monthly'!AL33+'PL Monthly'!AL34 -> -136332.62
B20: Amazon disbursement | C20: =0 -> 0 | D20: =0 -> 0 | E20: =0 -> 0 | F20: =E12 -> 18925.541 | G20: =F12 -> 38188.237 | H20: =G12 -> 57350.576 | I20: =H12 -> 83485.591 | J20: =I12 -> 104370.61 | K20: =J12 -> 125493.82 | L20: =K12 -> 146414.56 | M20: =L12 -> 167335.3 | ... AN20: =AM12 -> 275670.56
B21: JCT settlement | C21: =0 -> 0 | D21: =0 -> 0 | E21: =0 -> 0 | F21: =0 -> 0 | G21: =0 -> 0 | H21: =-(SUM(C13:G13)-SUM(C14:G14)) -> 8604.5663 | I21: =0 -> 0 | J21: =0 -> 0 | K21: =-(SUM(H13:J13)-SUM(H14:J14)) -> -2162.5013 | L21: =0 -> 0 | M21: =0 -> 0 | N21: =-(SUM(K13:M13)-SUM(K14:M14)) -> -12956.923 | O21: =0 -> 0 | P21: =0 -> 0 | Q21: =-(SUM(N13:P13)-SUM(N14:P14)) -> -13322.697 | R21: =0 -> 0 | S21: =0 -> 0 | T21: =-(SUM(Q13:S13)-SUM(Q14:S14)) -> -22189.864 | U21: =0 -> 0 | V21: =0 -> 0 | W21: =-(SUM(T13:V13)-SUM(T14:V14)) -> -22154.492 | X21: =0 -> 0 | Y21: =0 -> 0 | Z21: =-(SUM(W13:Y13)-SUM(W14:Y14)) -> -22225.236 | AA21: =0 -> 0 | AB21: =0 -> 0 | AC21: =-(SUM(Z13:AB13)-SUM(Z14:AB14)) -> -16120.464 | AD21: =0 -> 0 | AE21: =0 -> 0 | AF21: =-(SUM(AC13:AE13)-SUM(AC14:AE14)) -> -26849.736 | AG21: =0 -> 0 | AH21: =0 -> 0 | AI21: =-(SUM(AF13:AH13)-SUM(AF14:AH14)) -> -26806.936 | AJ21: =0 -> 0 | AK21: =0 -> 0 | AL21: =-(SUM(AI13:AK13)-SUM(AI14:AK14)) -> -26892.535 | AM21: =0 -> 0 | AN21: =0 -> 0
B22: Monthly net cash | C22: =C15+C16+C17+C18+C19+C20+C21 -> -591387.5 | D22: =D15+D16+D17+D18+D19+D20+D21 -> 0 | E22: =E15+E16+E17+E18+E19+E20+E21 -> -204670.83 | F22: =F15+F16+F17+F18+F19+F20+F21 -> -145068.21 | G22: =G15+G16+G17+G18+G19+G20+G21 -> -133024.26 | H22: =H15+H16+H17+H18+H19+H20+H21 -> -146846.37 | I22: =I15+I16+I17+I18+I19+I20+I21 -> -149382.21 | J22: =J15+J16+J17+J18+J19+J20+J21 -> -148033.18 | ... AN22: =AN15+AN16+AN17+AN18+AN19+AN20+AN21 -> 139337.93
B23: Cumulative cash | C23: =0+C22 -> -591387.5 | D23: =C23+D22 -> -591387.5 | E23: =D23+E22 -> -796058.33 | F23: =E23+F22 -> -941126.54 | G23: =F23+G22 -> -1074150.8 | H23: =G23+H22 -> -1220997.2 | I23: =H23+I22 -> -1370379.4 | J23: =I23+J22 -> -1518412.6 | K23: =J23+K22 -> -1659272 | ... AN23: =AM23+AN22 -> -3699548.3
B24: · payback flag | C24: =IF(1>C25,IF(C23>=0,1,0),0) -> 0 | D24: =IF(2>C25,IF(D23>=0,1,0),0) -> 0 | E24: =IF(3>C25,IF(E23>=0,1,0),0) -> 0 | F24: =IF(4>C25,IF(F23>=0,1,0),0) -> 0 | G24: =IF(5>C25,IF(G23>=0,1,0),0) -> 0 | H24: =IF(6>C25,IF(H23>=0,1,0),0) -> 0 | I24: =IF(7>C25,IF(I23>=0,1,0),0) -> 0 | J24: =IF(8>C25,IF(J23>=0,1,0),0) -> 0 | K24: =IF(9>C25,IF(K23>=0,1,0),0) -> 0 | L24: =IF(10>C25,IF(L23>=0,1,0),0) -> 0 | M24: =IF(11>C25,IF(M23>=0,1,0),0) -> 0 | N24: =IF(12>C25,IF(N23>=0,1,0),0) -> 0 | O24: =IF(13>C25,IF(O23>=0,1,0),0) -> 0 | P24: =IF(14>C25,IF(P23>=0,1,0),0) -> 0 | Q24: =IF(15>C25,IF(Q23>=0,1,0),0) -> 0 | R24: =IF(16>C25,IF(R23>=0,1,0),0) -> 0 | S24: =IF(17>C25,IF(S23>=0,1,0),0) -> 0 | T24: =IF(18>C25,IF(T23>=0,1,0),0) -> 0 | U24: =IF(19>C25,IF(U23>=0,1,0),0) -> 0 | V24: =IF(20>C25,IF(V23>=0,1,0),0) -> 0 | W24: =IF(21>C25,IF(W23>=0,1,0),0) -> 0 | X24: =IF(22>C25,IF(X23>=0,1,0),0) -> 0 | Y24: =IF(23>C25,IF(Y23>=0,1,0),0) -> 0 | Z24: =IF(24>C25,IF(Z23>=0,1,0),0) -> 0 | AA24: =IF(25>C25,IF(AA23>=0,1,0),0) -> 0 | AB24: =IF(26>C25,IF(AB23>=0,1,0),0) -> 0 | AC24: =IF(27>C25,IF(AC23>=0,1,0),0) -> 0 | AD24: =IF(28>C25,IF(AD23>=0,1,0),0) -> 0 | AE24: =IF(29>C25,IF(AE23>=0,1,0),0) -> 0 | AF24: =IF(30>C25,IF(AF23>=0,1,0),0) -> 0 | AG24: =IF(31>C25,IF(AG23>=0,1,0),0) -> 0 | AH24: =IF(32>C25,IF(AH23>=0,1,0),0) -> 0 | AI24: =IF(33>C25,IF(AI23>=0,1,0),0) -> 0 | AJ24: =IF(34>C25,IF(AJ23>=0,1,0),0) -> 0 | AK24: =IF(35>C25,IF(AK23>=0,1,0),0) -> 0 | AL24: =IF(36>C25,IF(AL23>=0,1,0),0) -> 0 | AM24: =IF(37>C25,IF(AM23>=0,1,0),0) -> 0 | AN24: =IF(38>C25,IF(AN23>=0,1,0),0) -> 0
B25: · trough position | C25: =MATCH(MIN(C23:AN23),C23:AN23,0) -> 35
B26: KPIs (live — follow the scenario switcher)
B27: Peak funding need (JPY) | C27: =-MIN(C23:AN23) -> 3888349.2
B28: Peak funding need (USD memo) | C28: =-MIN(C23:AN23)*a_cur_div/a_fx_jpy_per_usd -> 25922.328
B29: Payback month | C29: =IF(SUM(C24:AN24)=0,"n/a",MATCH(1,C24:AN24,0)+-2) -> n/a
B30: 3Y cumulative project cash | C30: =AN23 -> -3699548.3
B31: 3Y EBITDA (accrual) | C31: =SUM('PL Monthly'!C35:AL35) -> -3015200.2
B32: 3Y EBITDA - CAPEX (accrual memo) | C32: =SUM('PL Monthly'!C35:AL35)-a_act_capex_total/a_cur_div -> -3534400.2
B33: Gross Margin: (Price - Referral - FBA) / Price | C33: =(a_act_asp_jpy-a_act_referral_pu-a_fba_fee_net*(1+a_jct_rate_standard))/a_act_asp_jpy -> 0.77742857
B34: Net Contribution Margin (M7-12): (Rev - COGS - Fees - PPC) / Rev | C34: =IF(SUM('PL Monthly'!I12:N12)=0,0,(SUM('PL Monthly'!I12:N12)+SUM('PL Monthly'!I18:N18)+SUM('PL Monthly'!I19:N19)+SUM('PL Monthly'!I20:N20)+SUM('PL Monthly'!I21:N21)+SUM('PL Monthly'!I23:N23)+SUM('PL Monthly'!I24:N24)+SUM('PL Monthly'!I25:N25)+SUM('PL Monthly'!I26:N26)+SUM('PL Monthly'!I27:N27)+SUM('PL Monthly'!I29:N29))/SUM('PL Monthly'!I12:N12)) -> 0.14786872
B35: Terminal inventory (units, memo) | C35: =AN11 -> 0
B36: Terminal inventory (value, memo) | C36: =AN11*a_act_basis_pu/a_cur_div -> 0

Sheet Sensitivity
B2: Made for Doraemon | H2: ="Currency: "&a_currency&" · switch on the Dashboard" -> Currency: JPY · switch on the Dashboard
B4: Sensitivity
B5: One factor at a time on the base scenario, computed by the engine. This sheet is intentionally static (no formulas) — it shows full model re-runs, which a single spreadsheet formula cannot express; it refreshes on every rebuild.
B7: Driver | C7: Low: EBITDA 3Y | D7: Low: payback | E7: Low: peak ¥ | F7: High: EBITDA 3Y | G7: High: payback | H7: High: peak ¥
B8: asp | C8: =-3683843.26759786/a_cur_div -> -3683843.3 | D8: n/a | E8: =4466141.33420326/a_cur_div -> 4466141.3 | F8: =-2346557.16314647/a_cur_div -> -2346557.2 | G8: n/a | H8: =3318311.55604935/a_cur_div -> 3318311.6
B9: target_share | C9: =-3194960.15076052/a_cur_div -> -3194960.2 | D9: n/a | E9: =3897930.35216755/a_cur_div -> 3897930.4 | F9: =-2835440.27998382/a_cur_div -> -2835440.3 | G9: n/a | H9: =3902883.99510084/a_cur_div -> 3902884
B10: unit_cogs | C10: =-2297766.39774717/a_cur_div -> -2297766.4 | D10: n/a | E10: =3196178.12981315/a_cur_div -> 3196178.1 | F10: =-3732634.03299717/a_cur_div -> -3732634 | G10: n/a | H10: =4580520.32418815/a_cur_div -> 4580520.3
B11: tacos | C11: =-2497779.46537217/a_cur_div -> -2497779.5 | D11: n/a | E11: =3428577.41450065/a_cur_div -> 3428577.4 | F11: =-3532620.96537217/a_cur_div -> -3532621 | G11: n/a | H11: =4356052.11489157/a_cur_div -> 4356052.1
B12: ramp_months | C12: =-3014223.77034186/a_cur_div -> -3014223.8 | D12: n/a | E12: =3885544.65697034/a_cur_div -> 3885544.7 | F12: =-3016163.0342055/a_cur_div -> -3016163 | G12: n/a | H12: =3891140.17083398/a_cur_div -> 3891140.2
B13: cover_days | C13: =-3003202.83419517/a_cur_div -> -3003202.8 | D13: n/a | E13: =3782484.49037277/a_cur_div -> 3782484.5 | F13: =-3027206.83054917/a_cur_div -> -3027206.8 | G13: n/a | H13: =4020785.28800137/a_cur_div -> 4020785.3
B14: fee_drift | C14: =-3015200.21537217/a_cur_div -> -3015200.2 | D14: n/a | E14: =3888349.22700065/a_cur_div -> 3888349.2 | F14: =-3113337.48363035/a_cur_div -> -3113337.5 | G14: n/a | H14: =3972867.00315283/a_cur_div -> 3972867

Sheet Sources and Benchmarks
B2: Made for Doraemon
B4: Sources & Benchmarks
B5: Where every input comes from — click a source to open it. Reconciliation note: the research-stage screen used tax-inclusive revenue, gross published FBA fees and a supplier-proxy cost; this model uses net-of-tax revenue, net fees and domestic procurement cost. The conventions differ by design; the client GM>=40% gate refers to the research-stage convention.
B7: Input | C7: Value | D7: Layer | E7: Source (click to open) | F7: Confidence | G7: As of | H7: Note
B8: Amazon fee category | C8: Beauty, health & personal care | D8: pipeline | E8: mapped from niche category_group (amazon_jp_referral.yaml) | F8: med | G8: 2026-06-11
B9: Price — base | C9: 3500.0 | D9: pipeline | E9: enrichment live price band | F9: med | G9: 2026-06-11
B10: Price — optimistic | C10: 4200.0 | D10: pipeline | E10: enrichment live price band | F10: med | G10: 2026-06-11
B11: Price — pessimistic | C11: 2800.0 | D11: pipeline | E11: enrichment live price band | F11: med | G11: 2026-06-11
B12: Launch: certification & lab tests | C12: 100000 | D12: bundled | E12: category lab tests placeholder — category-dependent | F12: low | G12: 2026-06-11
B13: Launch: photo & A+ production | C13: 150000 | D13: bundled | E13: launch photography/A+ production | F13: low | G13: 2026-06-11
B14: Launch: contingency | C14: 0.1 | D14: bundled | E14: contingency on itemized CAPEX | F14: med | G14: 2026-06-11
B15: Launch: OEM tooling | C15: 0 | D15: bundled | E15: quote-based; enter with the OEM quote | F15: low | G15: 2026-06-11
B16: Launch: samples | C16: 50000 | D16: bundled | E16: sample rounds benchmark | F16: low | G16: 2026-06-11
B17: Launch: trademark | C17: 150000 | D17: bundled | E17: Cotobox trademark cost — https://cotobox.com/primer/registration-fee/; JPO fees — https://www.jpo.go.jp/system/process/tesuryo/hyou.html | F17: med | G17: 2026-06-11
B18: Launch: Vine reviews | C18: 22000 | D18: bundled | E18: Vine JP fees — https://www.hideandseek.co.jp/archives/7954 (¥0/¥10k/¥22k tiers) | F18: high | G18: 2026-06-11
B19: category buckets | C19: [['食品', 'food'], ['フード', 'food'], ['サプリ', 'food'], ['飲料', 'food'], ['ビューティ', 'co | D19: bundled | E19: internal mapping over the canonical niche base category groups | F19: med | G19: 2026-06-11
... B27: fallback package | C27: {'length_mm': 200, 'width_mm': 150, 'height_mm': 50, 'weight_g': 300} | D27: bundled | E27: category-median standard-size parcel | F27: low | G27: 2026-06-11
B28: FBA fulfillment fee / unit (computed) | C28: 377.27272727272725 | D28: computed | E28: amazon_jp_fba_fees.yaml via size tier (published tax-incl -> net) | F28: high | G28: 2026-06-11 | H28: computed in-workbook
B29: JPY per USD (memo) | C29: 150.0 | D29: project | E29: criteria.yaml | F29: med
B30: Influencers & affiliates / month | C30: 0 | D30: bundled | E30: internal default — set when creator marketing is planned | F30: low | G30: 2026-06-11
B31: Quality inspection / unit | C31: 0 | D31: bundled | E31: internal default — set per OEM contract | F31: low | G31: 2026-06-11
B32: Product liability insurance | C32: 3000 | D32: bundled | E32: Marsh Amazon seller insurance — https://affinity.marsh.com/amazonsellers/insights/amazon-sellers-insurance-requirements.html; domestic JP PL ¥20-50k/yr | F32: med | G32: 2026-06-11
B33: Tax settlement window (months) | C33: 3 | D33: bundled | E33: quarterly interim JCT payments | F33: med | G33: 2026-06-11
B34: Consumption tax rate (sales) | C34: 0.1 | D34: bundled | E34: NTA standard rate; 8% food only via explicit user override | F34: high | G34: 2026-06-11
B35: Consumption tax rate (services) | C35: 0.1 | D35: bundled | E35: NTA — fee de-JCT divisor, services always 10% | F35: high | G35: 2026-06-11
B36: Launch month (1-12) | C36: 8 | D36: bundled | E36: build month + lead window (default) | F36: low | G36: 2026-06-11
B37: Logistics to Amazon / unit | C37: 50 | D37: bundled | E37: FBA partner carrier (Yamato) — https://wac-works-ec.jp/amazon/fba-partner-career/ | F37: low | G37: 2026-06-11
B38: ltsf brackets | C38: [{'min_days': 271, 'max_days': 300, 'rate': 16.662}, {'min_days': 301, 'max_days | D38: bundled | E38: Seller Central JP 長期在庫追加手数料 — https://sellercentral.amazon.co.jp/help/hub/reference/external/GBJ9XBVWSBKZWD76; 366d+ ¥34.239 since Apr-2025, min ¥20/unit/mo from 2026-04-15 | F38: med | G38: 2026-06-11
B39: Management fee — yearly increase | C39: 0.0 | D39: bundled | E39: default | F39: high | G39: 2026-06-11
B40: Management fee — fixed / month | C40: 70000 | D40: bundled | E40: absorbs former admin defaults: accounting ¥50k (税理士 ¥500-700k/yr — https://www.zeiri4.com/c_1076/) + software ¥10k + misc ¥10k | F40: low | G40: 2026-06-11
B41: Management fee — type | C41: fixed | D41: bundled | E41: default off | F41: high | G41: 2026-06-11
... B59: reduced jct keywords | C59: ['食品', 'サプリ', '飲料', 'フード', 'お茶', 'コーヒー'] | D59: bundled | E59: NTA reduced rate — https://www.nta.go.jp/taxes/shiraberu/zeimokubetsu/shohi/keigenzeiritsu/index.htm | F59: high | G59: 2026-06-11
B60: Referral fee rate (computed) | C60: 0.104 | D60: computed | E60: amazon_jp_referral.yaml banded by category + base price (tax-excluded) | F60: high | G60: 2026-06-11 | H60: computed in-workbook from category + base price
B61: Refund admin fee cap | C61: 500 | D61: bundled | E61: same | F61: high | G61: 2026-06-11
B62: Refund admin fee | C62: 0.2 | D62: bundled | E62: Amazon refund administration fee — https://sellercentral.amazon.com/gp/help/external/DC3U6FWF4JJJJC7 (lesser of 20% of referral or ¥500) | F62: high | G62: 2026-06-11
B63: Return rate | C63: 0.02 | D63: pipeline | E63: niches.return_rate_360d | F63: med | G63: 2026-06-11
B64: return rate default | C64: {'food': 0.015, 'cosmetics': 0.035, 'apparel': 0.07, 'toys': 0.03, 'household': | D64: bundled | E64: trade.gov Japan eCommerce — https://www.trade.gov/country-commercial-guides/japan-ecommerce; Velocity Sellers category medians 2026 — https://velocitysellers.com | F64: low | G64: 2026-06-11
B65: Returns salvage | C65: 0.0 | D65: bundled | E65: internal default (conservative) | F65: med | G65: 2026-06-11
B66: seasonality | C66: [1.0, 1.0, 1.0, 1.0, 1.0, 1.0, 1.0, 1.0, 1.0, 1.0, 1.0, 1.0] | D66: bundled | E66: flat until Keepa collector ships | F66: low | G66: 2026-06-11
B67: Amazon payout cycle (days) | C67: 14 | D67: bundled | E67: Amazon JP disbursement cycle (~14d) — https://sellercentral.amazon.co.jp/help/hub/reference/external/G201051980 | F67: high | G67: 2026-06-11
B68: Market-share cap | C68: 0.25 | D68: bundled | E68: internal default — plausibility cap | F68: low | G68: 2026-06-11
B69: Shrinkage & write-offs | C69: 0.01 | D69: bundled | E69: Value Added Resource FBA reimbursement 2025 — https://www.valueaddedresource.net/amazon-fba-inventory-reimbursement-2025/ | F69: low | G69: 2026-06-11
B70: Storage rate Jan-Sep | C70: 5.16 | D70: bundled | E70: Amazon JP pricing 在庫保管手数料 — https://sell.amazon.co.jp/pricing | F70: high | G70: 2026-06-11 | H70: published tax-incl 5.676 -> net /1.10
B71: Storage rate Oct-Dec | C71: 9.169999999999998 | D71: bundled | E71: Amazon JP pricing 在庫保管手数料 — https://sell.amazon.co.jp/pricing | F71: high | G71: 2026-06-11 | H71: published tax-incl 10.087 -> net /1.10
B72: Amazon subscription | C72: 4900 | D72: bundled | E72: Amazon JP pricing 大口出品 — https://sell.amazon.co.jp/pricing | F72: high | G72: 2026-06-11
B73: Supplier tax-invoice credit | C73: 1.0 | D73: bundled | E73: NTA invoice system transitional credits — https://www.nta.go.jp/taxes/shiraberu/zeimokubetsu/shohi/keigenzeiritsu/invoice.htm | F73: med | G73: 2026-06-11
B74: Ad % relief (optimistic) | C74: -0.03 | D74: bundled | E74: scenario stress (-3pp per phase) | F74: low | G74: 2026-06-11
B75: Ad % stress (pessimistic) | C75: 0.05 | D75: bundled | E75: scenario stress (+5pp per phase) | F75: low | G75: 2026-06-11
B76: Ad spend % — end of year 1 | C76: 0.15 | D76: bundled | E76: benchmark band | F76: low | G76: 2026-06-11
B77: Ad spend % — launch (TACoS) | C77: 0.25 | D77: bundled | E77: markenote.jp JP CPC ¥50-300 — https://markenote.jp/amazon-ads-cpc/; JP agency ACoS consensus 20-30% steady, 40-60% launch | F77: low | G77: 2026-06-11
B78: Ad spend % — year 2 | C78: 0.12 | D78: bundled | E78: benchmark band | F78: low | G78: 2026-06-11
B79: Ad spend % — year 3 | C79: 0.1 | D79: bundled | E79: benchmark band | F79: low | G79: 2026-06-11
B80: Target market share | C80: 0.05 | D80: bundled | E80: internal default — single new entrant | F80: low | G80: 2026-06-11
B81: Share boost (optimistic) | C81: 1.3 | D81: bundled | E81: scenario stress | F81: low | G81: 2026-06-11
B82: Share stress (pessimistic) | C82: 0.7 | D82: bundled | E82: scenario stress | F82: low | G82: 2026-06-11
B83: Unit cost (procurement) | C83: 1575.0 | D83: bundled | E83: ECのミカタ 掛け率 — https://ecnomikata.com/ecnews/35771/; FORCE-R — https://force-r.co.jp/column/column-7555/; 資生販売 — https://shiseihanbai.biz/contents/learning-ratio-of-wholesale-price-to-retail-price/ | F83: low | G83: 2026-06-11 | H83: cogs-benchmark 掛け率 0.45 x base ASP (cosmetics) — replace with a supplier/OEM quote before decisions
B84: Package volume (computed) | C84: 0.648 | D84: computed | E84: package dims (L x W x H) | F84: high | G84: 2026-06-11 | H84: computed in-workbook
B85: Niche demand (units / year) | C85: 18000 | D85: pipeline | E85: enrichment.units_360d | F85: med | G85: 2026-06-11

Sheet Glossary
B2: Made for Doraemon
B4: Glossary
B5: What every line means. Scenarios are one-sided stress bundles, not jointly-coherent worlds — judge decisions on the base scenario plus Sensitivity. Where the unit cost is the wholesale benchmark (flag cogs-benchmark), treat the model as a screening placeholder: standard wholesale pricing rarely clears GM>=40% after Amazon fees; OEM manufacturing quotes are the realistic path for finalists.
B7: Line | C7: Name | D7: Definition
B8: R1 | C8: Units sold | D8: Niche demand x market share x launch ramp x seasonality (continuous units).
B9: R2 | C9: ASP (tax-incl) | D9: Average selling price on Amazon.co.jp, tax included (scenario-active).
B10: R3 | C10: Gross sales | D10: Units x ASP, tax-inclusive as displayed on the marketplace.
B11: R4 | C11: Output JCT | D11: Consumption tax carved out of tax-inclusive sales (rate/(1+rate)); computed on undiscounted gross and not reversed on returns - conservative.
B12: R5 | C12: Amazon Points | D12: Default 1% seller-funded points on JP listings (contra-revenue).
B13: R6 | C13: Promotions & deals | D13: Launch-heavy promo schedule; coupon/deal fee mechanics folded into the rate.
B14: R7 | C14: Returns | D14: Customer returns at the JP category benchmark rate (revenue reversal).
B15: R8 | C15: Net revenue | D15: Gross sales less output JCT, points, promotions, and returns.
B16: C1 | C16: Unit procurement cost | D16: Domestic purchase or OEM cost per unit, ex-JCT; non-creditable input-JCT share added when the supplier is not a qualified-invoice issuer.
B17: C2 | C17: Domestic logistics to FBA | D17: Supplier -> prep -> fulfillment center, per unit.
B18: C3 | C18: Inspection / QC | D18: Acceptance testing per unit (0 unless OEM QC is contracted).
... B48: CF7 | C48: JCT settlement | D48: Output JCT less input credits, remitted after each filing window.
